Workbook

Sheet Objekte
A1: Ordnungsnummer | B1: Name | C1: Link Objekt (URL) | D1: Charme/Ästhetik (1-5) | E1: Zimmer | F1: Bäder | G1: Grundstücksgröße (m²) | H1: Bebaute Fläche (m²) | I1: Garten zu bewirtschaften (m²) | J1: Location | K1: Entfernung Flughafen (km) | L1: Entfernung Flughafen (min) | M1: Entfernung Daia Haus (km) | N1: Entfernung Daia Haus (min) | O1: Entfernung Andratx (km) | P1: Entfernung Andratx (min) | Q1: Entfernung Ses Salines (km) | R1: Entfernung Ses Salines (min) | S1: Preis (€) | T1: €/m² (bebaut) | U1: €/m² (Grundstück) | V1: Renovierung (0-100) | W1: Bewirtschaftung (1-5, 5=pflegeleicht) | X1: Vermietlizenz (100/50/0) | Y1: Erreichbarkeit (0-100) | Z1: Score (0-100) | AA1: SortKey (intern) | AB1: Rang | AC1: Gebäudestruktur | AD1: Baujahr (geschätzt) | AE1: Letzte Renovierung (geschätzt) | AF1: Reno-Score (0-100) | AG1: Reno-Begründung | AH1: Kommentar | AI1: Beschreibung
A2: 1 | B2: Establiments — Das Volumen; 762m² zum Umdenken | C2: https://www.idealista.com/de/inmueble/106332052/mapa?utm_medium=socialmedia&utm_campaign=private_sendadtofriend&utm_source=copiedLink | D2: 4 | E2: 4 | F2: 5 | G2: 20262 | H2: 762 | I2: 19500 | J2: Establiments | K2: 16.5 | L2: 20 | M2: 30.5 | N2: 39 | O2: 34.1 | P2: 35 | Q2: 59.4 | R2: 53 | S2: 3600000 | T2: 4724 | U2: 178 | V2: 70 | W2: 3 | X2: 0 | Y2: 58.5 | Z2: 50 | AA2: 5.0020263e+13 | AB2: 6 | AC2: Haupthaus (2 Stockwerke + Turm), große Terrassen | AD2: ~1960s | AE2: ~2022 | AF2: 70 | AG2: Traditional country house, fully renovated with high-end kitchen (Gaggenau/Bora), modern open-plan layout. No build year listed suggests older structure. Excel comment notes 'Haupthaus (2 Stockwerke + Turm), große Terrassen'. Well-renovated but original structure is old. Old=4 → 70. | AI2: Riesig, tolle Lage — aber nur 4 Zimmer. Umbau nötig, dann ein Monster.
A3: 2 | B3: Binissalem — Platz für alle; 8 Zimmer, endlose Gärten | C3: https://www.engelvoelkers.com/es/de/exposes/6971ac2a-f182-5703-a001-2c6f306cd2ae?utm_source=expose_sharing&utm_medium=copy_link | D3: 4 | E3: 8 | F3: 6 | G3: 8261 | H3: 400 | I3: 7861 | J3: Binissalem | K3: 29 | L3: 24 | M3: 36.2 | N3: 42 | O3: 51.6 | P3: 42 | Q3: 71.9 | R3: 57 | S3: 3400000 | T3: 8500 | U3: 412 | V3: 72 | W3: 3 | X3: 0 | Y3: 49.3 | Z3: 57.5 | AA3: 5.7508261e+13 | AB3: 3 | AC3: Haupthaus + 2 separate Gästehäuser | AD3: 2002 | AE3: ~2022 | AF3: 72 | AG3: Built 2002, comprehensively modernized with PV, Starlink, modern insulation. Condition rated 'Sehr gut'. Only 23 years old with full modernization. Excel: 'Sehr schön, evtl. Ausbaumöglichkeit'. Old=4 → 72. | AH3: Sehr schön, evtl. Ausbaumöglichkeit für zusätzliches Zimmer prüfen | AI3: Sommer im Garten, Großmutter zum Abendessen — alles nah, alles einfach.
A4: 3 | B4: Establiments — Charme-Refugium; altes Steinhaus mit Charakter | C4: https://www.idealista.com/de/inmueble/106744049/foto/1/?utm_medium=socialmedia&utm_campaign=private_sendadtofriend&utm_source=copiedLink | D4: 5 | E4: 7 | F4: 7 | G4: 14393 | H4: 601 | I4: 13792 | J4: Establiments | K4: 16.5 | L4: 20 | M4: 30.5 | N4: 39 | O4: 34.1 | P4: 35 | Q4: 59.4 | R4: 53 | S4: 4500000 | T4: 7488 | U4: 313 | V4: 62 | W4: 2 | X4: 0 | Y4: 58.5 | Z4: 58.6 | AA4: 5.8614394e+13 | AB4: 2 | AC4: Haupthaus (5 SZ, 6 Bäder) + unabhängiges Gästehaus (2 SZ, 1 Bad) | AD4: 1980 | AE4: ~2015 | AF4: 62 | AG4: Built 1980 (45 years old), maintained in Mallorcan country house style with modern amenities (underfloor heating, designer kitchen). Excel: 'Gute Raumanzahl + Gästehaus, innen nicht ganz überzeugend'. Interior not fully convincing suggests renovation is partial. Old=4 → 62. | AH4: Gute Raumanzahl + Gästehaus, innen nicht ganz überzeugend | AI4: Alte Mauern, warmes Licht — ein Haus das die Kinder nie vergessen werden.
A5: 4 | B5: Palmanyola — Klein aber Wow; Designvilla vor den Toren Palmas | C5: https://www.idealista.com/de/inmueble/109708161/plano/2/?utm_medium=socialmedia&utm_campaign=private_sendadtofriend&utm_source=copiedLink | D5: 4 | E5: 5 | F5: 5 | G5: 2500 | H5: 670 | I5: 1830 | J5: Palmanyola | K5: 16.6 | L5: 16 | M5: 18 | N5: 23 | O5: 36.2 | P5: 32 | Q5: 59.5 | R5: 50 | S5: 5600000 | T5: 8358 | U5: 2240 | V5: 78 | W5: 4 | X5: 0 | Y5: 76 | Z5: 31.3 | AA5: 3.1302501e+13 | AB5: 12 | AC5: Freistehendes Haus mit Pool und Garten | AD5: ~1990s | AE5: ~2024 | AF5: 78 | AG5: Description explicitly says 'komplett kernsaniert' – complete core renovation. Modern open kitchen, fireplace, 2 floors with 670m². Excel old=3 probably reflected pre-renovation state or plot size concern ('Grundstück evtl. zu klein'). Actual condition is excellent post-renovation. → 78. | AH5: Sehr modern, Grundstück evtl. zu klein | AI5: Modern, sofort bezugsfertig, nah dran — aber Grundstück zu klein für drei Kinder.
A6: 5 | B6: Santa Maria — Potenzial pur; Rohling in Traumlage | C6: https://www.idealista.com/de/inmueble/106300856/foto/17/?utm_medium=socialmedia&utm_campaign=private_sendadtofriend&utm_source=copiedLink | D6: 4 | E6: 5 | F6: 5 | G6: 29307 | H6: 500 | I6: 28807 | J6: Santa Maria del Cami | K6: 21 | L6: 16 | M6: 24.2 | N6: 32 | O6: 43.6 | P6: 34 | Q6: 63.8 | R6: 49 | S6: 4100000 | T6: 8200 | U6: 140 | V6: 48 | W6: 3 | X6: 0 | Y6: 66 | Z6: 43.5 | AA6: 4.3529308e+13 | AB6: 10 | AC6: Landhaus mit Pool und Terrassen, teils unfertig | AD6: 2024 | AE6: n/a (new build) | AF6: 48 | AG6: New build 2024 but still under construction ('In Bearbeitung'). Excel: 'Gute Lage, einiges noch nicht fertig'. While the finished product will be new, incomplete status means uncertain timeline and finishing quality. Old=3 → 48. | AH6: Gute Lage, einiges noch nicht fertig | AI6: Traumlage, nah am Flughafen — aber unfertig. Mit kleinen Kindern erstmal stressig.
A7: 6 | B7: Campos — Zum Selbermachen; ehrliche Finca, ehrlicher Preis | C7: https://www.idealista.com/de/inmueble/81539590/?utm_medium=socialmedia&utm_campaign=private_sendadtofriend&utm_source=copiedLink | D7: 4 | E7: 6 | F7: 5 | G7: 11700 | H7: 356 | I7: 11344 | J7: Campos | K7: 29.9 | L7: 21 | M7: 64.2 | N7: 57 | O7: 67.9 | P7: 50 | Q7: 12.2 | R7: 13 | S7: 2850000 | T7: 8006 | U7: 244 | V7: 50 | W7: 3 | X7: 0 | Y7: 57.8 | Z7: 44 | AA7: 4.40117e+13 | AB7: 9 | AC7: Modernes Landhaus mit großem Pool und Garten | AD7: ~1990s | AE7: ~2010 | AF7: 50 | AG7: No build year, 'In Bearbeitung' status, no heating system. Excel: 'Interessante Substanz, viel Interior-Arbeit, evtl. günstiger'. Needs significant interior renovation work. Good bones but unfinished. Old=4 seems generous; actual condition warrants 50. | AH7: Interessante Substanz, viel Interior-Arbeit, evtl. günstiger | AI7: Solide Basis, fairer Preis — aber hier muss noch Hand angelegt werden.
A8: 7 | B8: Sa Ràpita — Strandgold; aufwachen, Es Trenc, fertig | C8: https://www.idealista.com/de/inmueble/109467637/foto/18/?utm_medium=socialmedia&utm_campaign=private_sendadtofriend&utm_source=copiedLink | D8: 4 | E8: 5 | F8: 5 | G8: 30000 | H8: 533 | I8: 29467 | J8: Sa Ràpita | K8: 35 | L8: 28 | M8: 69.4 | N8: 64 | O8: 73.1 | P8: 58 | Q8: 14.9 | R8: 17 | S8: 3950000 | T8: 7411 | U8: 132 | V8: 68 | W8: 2 | X8: 0 | Y8: 42 | Z8: 37.4 | AA8: 3.7430001e+13 | AB8: 11 | AC8: Haupthaus mit ausgedehntem Grundstück und Pool | AD8: 2024 | AE8: n/a (new build) | AF8: 68 | AG8: New build 2024 with modern design and natural elements. 30,000m² plot near Es Trenc beach. No 'In Bearbeitung' flag suggests more complete than Santa Maria property. Excel old=3 seems low for a 2024 new build; possibly reflected other concerns. → 68. | AH8: Nähe Es Trenc | AI8: Strand vor der Tür, perfekt für Sommer — aber über eine Stunde zum Familienhaus.
A9: 8 | B9: Sa Ràpita — Vision 1800; 5 Hektar warten auf deine Handschrift | C9: https://www.idealista.com/de/inmueble/106134268/video/1/?utm_medium=socialmedia&utm_campaign=private_sendadtofriend&utm_source=copiedLink | D9: 3 | E9: 6 | F9: 3 | G9: 51000 | H9: 680 | I9: 50320 | J9: Sa Ràpita | K9: 35 | L9: 28 | M9: 69.4 | N9: 64 | O9: 73.1 | P9: 58 | Q9: 14.9 | R9: 17 | S9: 2950000 | T9: 4338 | U9: 58 | V9: 30 | W9: 4 | X9: 0 | Y9: 42 | Z9: 49.3 | AA9: 4.9351001e+13 | AB9: 7 | AC9: Haus mit Pool in ruhiger Lage | AD9: 1800 | AE9: unknown | AF9: 30 | AG9: Built around 1800 – over 200 years old. 'In Bearbeitung' and Excel says 'Hier könnte sich Mathieu verwirklichen' (creative project). Traditional Mallorcan farmhouse needing significant work. Described as 'gut erhalten' (well-maintained) but very old. Old=3 → 30. | AH9: Hier könnte sich Mathieu verwirklichen 😉 | AI9: Für Visionäre — aber nichts für 6 Wochen im Jahr. Ehrlich gesagt: zu viel Projekt.
A10: 9 | B10: Sencelles — 13 Hektar Paradies; dein eigenes Landgut | C10: https://ev-mallorca.com/en/mallorca-property/excellent-estate-with-its-own-vineyard-olive-grove-and-incredible-charm-W-02Q8YG | D10: 5 | E10: 6 | F10: 5 | G10: 132500 | H10: 682 | I10: 131818 | J10: Sencelles | K10: 31.7 | L10: 26 | M10: 38.9 | N10: 44 | O10: 54.3 | P10: 45 | Q10: 44 | R10: 45 | S10: 3900000 | T10: 5718 | U10: 29 | V10: 85 | W10: 2 | X10: 50 | Y10: 44.8 | Z10: 59.8 | AA10: 5.9932501e+13 | AB10: 1 | AC10: Haupthaus + Gästeapartment + Studio, Weinberg & Olivenhain | AD10: 1890 | AE10: ~2020 | AF10: 85 | AG10: Built 1890 but rated neuwertig (5) in Excel. Must have undergone comprehensive luxury renovation. 132,000m²+ estate with vineyard and olive grove. The 'incredible charm' title plus neuwertig rating suggests top-quality restoration. Historic character + modern luxury. → 85. | AI10: So viel Platz, dass sich drei kleine Entdecker darin verlaufen können.
A11: 10 | B11: Ses Salines — Neubau Deluxe; einziehen und leben | C11: https://ev-mallorca.com/en/mallorca-property/unique-designer-house-in-a-quiet-location-W-0475DS | D11: 5 | E11: 5 | F11: 5 | G11: 23800 | H11: 399 | I11: 23401 | J11: Ses Salines | K11: 42.2 | L11: 34 | M11: 76.5 | N11: 70 | O11: 80.2 | P11: 63 | Q11: 0 | R11: 0 | S11: 5450000 | T11: 13659 | U11: 229 | V11: 98 | W11: 4 | X11: 0 | Y11: 33.3 | Z11: 31 | AA11: 3.10238e+13 | AB11: 13 | AC11: Einzelgebäude (einstöckig), Neubau 2025 | AD11: 2025 | AE11: n/a (new build) | AF11: 98 | AG11: Brand new construction 2025. Designer house, single-story, quiet location. As new as it gets. Old=5 → 98. | AI11: Koffer abstellen, fertig. Aber weit vom Familienhaus und über Budget.
A12: 11 | B12: Moscari — Architekten-Traum; Design trifft Serra de Tramuntana | C12: https://ev-mallorca.com/en/mallorca-property/where-contemporary-design-blends-in-perfect-harmony-with-the-mediterranean-landscape-W-02NQDS | D12: 5 | E12: 5 | F12: 5 | G12: 19811 | H12: 832 | I12: 18979 | J12: Moscari | K12: 46.3 | L12: 34 | M12: 53.5 | N12: 52 | O12: 68.9 | P12: 52 | Q12: 64.6 | R12: 62 | S12: 3950000 | T12: 4748 | U12: 199 | V12: 92 | W12: 4 | X12: 0 | Y12: 29.3 | Z12: 48.8 | AA12: 4.8819812e+13 | AB12: 8 | AC12: Haupthaus + separater Gästebereich | AD12: 2018 | AE12: n/a | AF12: 92 | AG12: Built 2018, only 8 years old. Contemporary design, large 832m² living area. Wheelchair accessible and senior-oriented suggests high-spec modern build. Excel: 'Haupthaus + separater Gästebereich'. Old=5 → 92. | AI12: Aufwachen mit Bergblick, einschlafen mit Stille — aber weit weg vom Familienhaus.
A13: 12 | B13: Campos — Finca mit Lizenz; 14 Hektar mallorquinischer Traum | C13: https://ev-mallorca.com/en/mallorca-property/dreamlike-finca-with-rental-license-near-es-trenc-W-02ZICD | D13: 4 | E13: 6 | F13: 6 | G13: 14200 | H13: 436 | I13: 13764 | J13: Campos | K13: 30.6 | L13: 23 | M13: 64.2 | N13: 57 | O13: 67.9 | P13: 50 | Q13: 12.2 | R13: 13 | S13: 3490000 | T13: 8005 | U13: 246 | V13: 65 | W13: 2 | X13: 100 | Y13: 56.2 | Z13: 54.4 | AA13: 5.44142e+13 | AB13: 4 | AC13: Haupthaus + separater Gebäudeteil (L-Form), Sportanlagen | AD13: 1997 | AE13: 2014 | AF13: 65 | AG13: Built 1997, last restored 2014 (12 years ago). Well-equipped with PV, underfloor heating, A/C. Sports facilities. But restoration is over a decade old now. Excel: 'Haupthaus + separater Gebäudeteil (L-Form), Sportanlagen'. Old=4 → 65. | AI13: Vermieten wenn ihr nicht da seid, ankommen wenn ihr wollt — die Finca rechnet sich.
A14: 13 | B14: Bunyola — Berglage mit Lizenz; Tramuntana vor der Tür | C14: https://www.idealista.com/inmueble/110322709/ | D14: 5 | E14: 6 | F14: 5 | G14: 14785 | H14: 355 | J14: Bunyola | K14: 23.8 | L14: 20 | M14: 14.8 | N14: 20 | O14: 46.4 | P14: 38 | Q14: 66.7 | R14: 53 | S14: 3500000 | T14: 9859 | U14: 237 | V14: 70 | W14: 3 | X14: 100 | Y14: 76 | Z14: 51.2 | AA14: 5.1214785e+13 | AB14: 5 | AC14: Haupthaus + Gästehaus (70m²) + Turm (30m²) | AD14: 2008 | AE14: unknown | AF14: 70 | AG14: Built 2008 (18 years old), good condition ('buen estado'). Single-story, 6 rooms, 5 baths. Excel: 'Haupthaus + Gästehaus (70m²) + Turm (30m²)'. Solid build age with good condition rating. Old=4 → 70. | AI14: 20 Minuten zum Familienhaus, Berge vor der Tür, Gäste im Haus — alles gleichzeitig.
A15: 14 | D15: 5 | T15: =IFERROR(IF($Q15="","",$Q15/$H15),"") | U15: =IFERROR(IF($Q15="","",$Q15/$G15),"") | V15: 4 | W15: 3 | Y15: =IF(AND($L15="",$N15="",$P15=""),"",ROUND((IF($L15="",0,IF($L15<=Einstellungen!$B$16,100,IF($L15<=Einstellungen!$C$16,80+(100-80)*(Einstellungen!$C$16-$L15)/(Einstellungen!$C$16-Einstellungen!$B$16),IF($L15<=Einstellungen!$D$16,80*(Einstellungen!$D$16-$L15)/(Einstellungen!$D$16-Einstellungen!$C$16),0))))*Einstellungen!$E$16+IF($N15="",0,IF($N15<=Einstellungen!$B$17,100,IF($N15<=Einstellungen!$C$17,80+(100-80)*(Einstellungen!$C$17-$N15)/(Einstellungen!$C$17-Einstellungen!$B$17),IF($N15<=Einstellungen!$D$17,80*(Einstellungen!$D$17-$N15)/(Einstellungen!$D$17-Einstellungen!$C$17),0))))*Einstellungen!$E$17+IF($P15="",0,IF($P15<=Einstellungen!$B$18,100,IF($P15<=Einstellungen!$C$18,80+(100-80)*(Einstellungen!$C$18-$P15)/(Einstellungen!$C$18-Einstellungen!$B$18),IF($P15<=Einstellungen!$D$18,80*(Einstellungen!$D$18-$P15)/(Einstellungen!$D$18-Einstellungen!$C$18),0))))*Einstellungen!$E$18)/(Einstellungen!$E$16+Einstellungen!$E$17+Einstellungen!$E$18),0)) | Z15: =IF(AND($E15="",$D15="",$G15="",$V15="",$Q15="",$T15="",$W15="",$U15=""),"",ROUND(IF($E15="",0,IF($E15<Einstellungen!$B$21,0,IF($E15>=Einstellungen!$B$22,100,($E15-Einstellungen!$B$21)/(Einstellungen!$B$22-Einstellungen!$B$21)*100)))/100*Einstellungen!$B$5+IF($W15="",0,$W15/100)*Einstellungen!$B$6+(IF($G15="",0,MAX(0,MIN(100,($G15-Einstellungen!$B$25)/(Einstellungen!$B$26-Einstellungen!$B$25)*100)))+IF($I15="",0,MAX(0,MIN(100,($I15-Einstellungen!$B$27)/(Einstellungen!$B$28-Einstellungen!$B$27)*100))))/2/100*Einstellungen!$B$7+IF($V15="",0,$V15/100)*Einstellungen!$B$8+IF($R15="",0,MAX(0,MIN(100,(Einstellungen!$B$32-$R15)/(Einstellungen!$B$32-Einstellungen!$B$31)*100)))/100*Einstellungen!$B$9+IF($D15="",0,$D15/5*100)/100*Einstellungen!$B$10+IF($AD15="",0,$AD15)/100*Einstellungen!$B$11+IF($U15="",0,$U15/5*100)/100*Einstellungen!$B$12,0)) | AA15: =IF($X15="","",$X15*1000000000000+IF($G15="",0,$G15)*1000000+IF($H15="",0,$H15)*1000+IF($I15="",0,$I15)+IF($N15="",0,MAX(0,1000-$N15))/1000+IF($A15="",0,$A15)/1000000) | AB15: =IF($Y15="","",_xludf.RANK.EQ($Y15,$Y$2:$Y$201,0)) | AC15: Unabhängiges Chalet mit Pool und Bergblick
T16: =IFERROR(IF($Q16="","",$Q16/$H16),"") | U16: =IFERROR(IF($Q16="","",$Q16/$G16),"") | Y16: =IF(AND($L16="",$N16="",$P16=""),"",ROUND((IF($L16="",0,IF($L16<=Einstellungen!$B$16,100,IF($L16<=Einstellungen!$C$16,80+(100-80)*(Einstellungen!$C$16-$L16)/(Einstellungen!$C$16-Einstellungen!$B$16),IF($L16<=Einstellungen!$D$16,80*(Einstellungen!$D$16-$L16)/(Einstellungen!$D$16-Einstellungen!$C$16),0))))*Einstellungen!$E$16+IF($N16="",0,IF($N16<=Einstellungen!$B$17,100,IF($N16<=Einstellungen!$C$17,80+(100-80)*(Einstellungen!$C$17-$N16)/(Einstellungen!$C$17-Einstellungen!$B$17),IF($N16<=Einstellungen!$D$17,80*(Einstellungen!$D$17-$N16)/(Einstellungen!$D$17-Einstellungen!$C$17),0))))*Einstellungen!$E$17+IF($P16="",0,IF($P16<=Einstellungen!$B$18,100,IF($P16<=Einstellungen!$C$18,80+(100-80)*(Einstellungen!$C$18-$P16)/(Einstellungen!$C$18-Einstellungen!$B$18),IF($P16<=Einstellungen!$D$18,80*(Einstellungen!$D$18-$P16)/(Einstellungen!$D$18-Einstellungen!$C$18),0))))*Einstellungen!$E$18)/(Einstellungen!$E$16+Einstellungen!$E$17+Einstellungen!$E$18),0)) | Z16: =IF(AND($E16="",$D16="",$G16="",$V16="",$Q16="",$T16="",$W16="",$U16=""),"",ROUND(IF($E16="",0,IF($E16<Einstellungen!$B$21,0,IF($E16>=Einstellungen!$B$22,100,($E16-Einstellungen!$B$21)/(Einstellungen!$B$22-Einstellungen!$B$21)*100)))/100*Einstellungen!$B$5+IF($W16="",0,$W16/100)*Einstellungen!$B$6+(IF($G16="",0,MAX(0,MIN(100,($G16-Einstellungen!$B$25)/(Einstellungen!$B$26-Einstellungen!$B$25)*100)))+IF($I16="",0,MAX(0,MIN(100,($I16-Einstellungen!$B$27)/(Einstellungen!$B$28-Einstellungen!$B$27)*100))))/2/100*Einstellungen!$B$7+IF($V16="",0,$V16/100)*Einstellungen!$B$8+IF($R16="",0,MAX(0,MIN(100,(Einstellungen!$B$32-$R16)/(Einstellungen!$B$32-Einstellungen!$B$31)*100)))/100*Einstellungen!$B$9+IF($D16="",0,$D16/5*100)/100*Einstellungen!$B$10+IF($AD16="",0,$AD16)/100*Einstellungen!$B$11+IF($U16="",0,$U16/5*100)/100*Einstellungen!$B$12,0)) | AA16: =IF($X16="","",$X16*1000000000000+IF($G16="",0,$G16)*1000000+IF($H16="",0,$H16)*1000+IF($I16="",0,$I16)+IF($N16="",0,MAX(0,1000-$N16))/1000+IF($A16="",0,$A16)/1000000) | AB16: =IF($Y16="","",_xludf.RANK.EQ($Y16,$Y$2:$Y$201,0))
T17: =IFERROR(IF($Q17="","",$Q17/$H17),"") | U17: =IFERROR(IF($Q17="","",$Q17/$G17),"") | Y17: =IF(AND($L17="",$N17="",$P17=""),"",ROUND((IF($L17="",0,IF($L17<=Einstellungen!$B$16,100,IF($L17<=Einstellungen!$C$16,80+(100-80)*(Einstellungen!$C$16-$L17)/(Einstellungen!$C$16-Einstellungen!$B$16),IF($L17<=Einstellungen!$D$16,80*(Einstellungen!$D$16-$L17)/(Einstellungen!$D$16-Einstellungen!$C$16),0))))*Einstellungen!$E$16+IF($N17="",0,IF($N17<=Einstellungen!$B$17,100,IF($N17<=Einstellungen!$C$17,80+(100-80)*(Einstellungen!$C$17-$N17)/(Einstellungen!$C$17-Einstellungen!$B$17),IF($N17<=Einstellungen!$D$17,80*(Einstellungen!$D$17-$N17)/(Einstellungen!$D$17-Einstellungen!$C$17),0))))*Einstellungen!$E$17+IF($P17="",0,IF($P17<=Einstellungen!$B$18,100,IF($P17<=Einstellungen!$C$18,80+(100-80)*(Einstellungen!$C$18-$P17)/(Einstellungen!$C$18-Einstellungen!$B$18),IF($P17<=Einstellungen!$D$18,80*(Einstellungen!$D$18-$P17)/(Einstellungen!$D$18-Einstellungen!$C$18),0))))*Einstellungen!$E$18)/(Einstellungen!$E$16+Einstellungen!$E$17+Einstellungen!$E$18),0)) | Z17: =IF(AND($E17="",$D17="",$G17="",$V17="",$Q17="",$T17="",$W17="",$U17=""),"",ROUND(IF($E17="",0,IF($E17<Einstellungen!$B$21,0,IF($E17>=Einstellungen!$B$22,100,($E17-Einstellungen!$B$21)/(Einstellungen!$B$22-Einstellungen!$B$21)*100)))/100*Einstellungen!$B$5+IF($W17="",0,$W17/100)*Einstellungen!$B$6+(IF($G17="",0,MAX(0,MIN(100,($G17-Einstellungen!$B$25)/(Einstellungen!$B$26-Einstellungen!$B$25)*100)))+IF($I17="",0,MAX(0,MIN(100,($I17-Einstellungen!$B$27)/(Einstellungen!$B$28-Einstellungen!$B$27)*100))))/2/100*Einstellungen!$B$7+IF($V17="",0,$V17/100)*Einstellungen!$B$8+IF($R17="",0,MAX(0,MIN(100,(Einstellungen!$B$32-$R17)/(Einstellungen!$B$32-Einstellungen!$B$31)*100)))/100*Einstellungen!$B$9+IF($D17="",0,$D17/5*100)/100*Einstellungen!$B$10+IF($AD17="",0,$AD17)/100*Einstellungen!$B$11+IF($U17="",0,$U17/5*100)/100*Einstellungen!$B$12,0)) | AA17: =IF($X17="","",$X17*1000000000000+IF($G17="",0,$G17)*1000000+IF($H17="",0,$H17)*1000+IF($I17="",0,$I17)+IF($N17="",0,MAX(0,1000-$N17))/1000+IF($A17="",0,$A17)/1000000) | AB17: =IF($Y17="","",_xludf.RANK.EQ($Y17,$Y$2:$Y$201,0))
T18: =IFERROR(IF($Q18="","",$Q18/$H18),"") | U18: =IFERROR(IF($Q18="","",$Q18/$G18),"") | Y18: =IF(AND($L18="",$N18="",$P18=""),"",ROUND((IF($L18="",0,IF($L18<=Einstellungen!$B$16,100,IF($L18<=Einstellungen!$C$16,80+(100-80)*(Einstellungen!$C$16-$L18)/(Einstellungen!$C$16-Einstellungen!$B$16),IF($L18<=Einstellungen!$D$16,80*(Einstellungen!$D$16-$L18)/(Einstellungen!$D$16-Einstellungen!$C$16),0))))*Einstellungen!$E$16+IF($N18="",0,IF($N18<=Einstellungen!$B$17,100,IF($N18<=Einstellungen!$C$17,80+(100-80)*(Einstellungen!$C$17-$N18)/(Einstellungen!$C$17-Einstellungen!$B$17),IF($N18<=Einstellungen!$D$17,80*(Einstellungen!$D$17-$N18)/(Einstellungen!$D$17-Einstellungen!$C$17),0))))*Einstellungen!$E$17+IF($P18="",0,IF($P18<=Einstellungen!$B$18,100,IF($P18<=Einstellungen!$C$18,80+(100-80)*(Einstellungen!$C$18-$P18)/(Einstellungen!$C$18-Einstellungen!$B$18),IF($P18<=Einstellungen!$D$18,80*(Einstellungen!$D$18-$P18)/(Einstellungen!$D$18-Einstellungen!$C$18),0))))*Einstellungen!$E$18)/(Einstellungen!$E$16+Einstellungen!$E$17+Einstellungen!$E$18),0)) | Z18: =IF(AND($E18="",$D18="",$G18="",$V18="",$Q18="",$T18="",$W18="",$U18=""),"",ROUND(IF($E18="",0,IF($E18<Einstellungen!$B$21,0,IF($E18>=Einstellungen!$B$22,100,($E18-Einstellungen!$B$21)/(Einstellungen!$B$22-Einstellungen!$B$21)*100)))/100*Einstellungen!$B$5+IF($W18="",0,$W18/100)*Einstellungen!$B$6+(IF($G18="",0,MAX(0,MIN(100,($G18-Einstellungen!$B$25)/(Einstellungen!$B$26-Einstellungen!$B$25)*100)))+IF($I18="",0,MAX(0,MIN(100,($I18-Einstellungen!$B$27)/(Einstellungen!$B$28-Einstellungen!$B$27)*100))))/2/100*Einstellungen!$B$7+IF($V18="",0,$V18/100)*Einstellungen!$B$8+IF($R18="",0,MAX(0,MIN(100,(Einstellungen!$B$32-$R18)/(Einstellungen!$B$32-Einstellungen!$B$31)*100)))/100*Einstellungen!$B$9+IF($D18="",0,$D18/5*100)/100*Einstellungen!$B$10+IF($AD18="",0,$AD18)/100*Einstellungen!$B$11+IF($U18="",0,$U18/5*100)/100*Einstellungen!$B$12,0)) | AA18: =IF($X18="","",$X18*1000000000000+IF($G18="",0,$G18)*1000000+IF($H18="",0,$H18)*1000+IF($I18="",0,$I18)+IF($N18="",0,MAX(0,1000-$N18))/1000+IF($A18="",0,$A18)/1000000) | AB18: =IF($Y18="","",_xludf.RANK.EQ($Y18,$Y$2:$Y$201,0))
T19: =IFERROR(IF($Q19="","",$Q19/$H19),"") | U19: =IFERROR(IF($Q19="","",$Q19/$G19),"") | Y19: =IF(AND($L19="",$N19="",$P19=""),"",ROUND((IF($L19="",0,IF($L19<=Einstellungen!$B$16,100,IF($L19<=Einstellungen!$C$16,80+(100-80)*(Einstellungen!$C$16-$L19)/(Einstellungen!$C$16-Einstellungen!$B$16),IF($L19<=Einstellungen!$D$16,80*(Einstellungen!$D$16-$L19)/(Einstellungen!$D$16-Einstellungen!$C$16),0))))*Einstellungen!$E$16+IF($N19="",0,IF($N19<=Einstellungen!$B$17,100,IF($N19<=Einstellungen!$C$17,80+(100-80)*(Einstellungen!$C$17-$N19)/(Einstellungen!$C$17-Einstellungen!$B$17),IF($N19<=Einstellungen!$D$17,80*(Einstellungen!$D$17-$N19)/(Einstellungen!$D$17-Einstellungen!$C$17),0))))*Einstellungen!$E$17+IF($P19="",0,IF($P19<=Einstellungen!$B$18,100,IF($P19<=Einstellungen!$C$18,80+(100-80)*(Einstellungen!$C$18-$P19)/(Einstellungen!$C$18-Einstellungen!$B$18),IF($P19<=Einstellungen!$D$18,80*(Einstellungen!$D$18-$P19)/(Einstellungen!$D$18-Einstellungen!$C$18),0))))*Einstellungen!$E$18)/(Einstellungen!$E$16+Einstellungen!$E$17+Einstellungen!$E$18),0)) | Z19: =IF(AND($E19="",$D19="",$G19="",$V19="",$Q19="",$T19="",$W19="",$U19=""),"",ROUND(IF($E19="",0,IF($E19<Einstellungen!$B$21,0,IF($E19>=Einstellungen!$B$22,100,($E19-Einstellungen!$B$21)/(Einstellungen!$B$22-Einstellungen!$B$21)*100)))/100*Einstellungen!$B$5+IF($W19="",0,$W19/100)*Einstellungen!$B$6+(IF($G19="",0,MAX(0,MIN(100,($G19-Einstellungen!$B$25)/(Einstellungen!$B$26-Einstellungen!$B$25)*100)))+IF($I19="",0,MAX(0,MIN(100,($I19-Einstellungen!$B$27)/(Einstellungen!$B$28-Einstellungen!$B$27)*100))))/2/100*Einstellungen!$B$7+IF($V19="",0,$V19/100)*Einstellungen!$B$8+IF($R19="",0,MAX(0,MIN(100,(Einstellungen!$B$32-$R19)/(Einstellungen!$B$32-Einstellungen!$B$31)*100)))/100*Einstellungen!$B$9+IF($D19="",0,$D19/5*100)/100*Einstellungen!$B$10+IF($AD19="",0,$AD19)/100*Einstellungen!$B$11+IF($U19="",0,$U19/5*100)/100*Einstellungen!$B$12,0)) | AA19: =IF($X19="","",$X19*1000000000000+IF($G19="",0,$G19)*1000000+IF($H19="",0,$H19)*1000+IF($I19="",0,$I19)+IF($N19="",0,MAX(0,1000-$N19))/1000+IF($A19="",0,$A19)/1000000) | AB19: =IF($Y19="","",_xludf.RANK.EQ($Y19,$Y$2:$Y$201,0))
T20: =IFERROR(IF($Q20="","",$Q20/$H20),"") | U20: =IFERROR(IF($Q20="","",$Q20/$G20),"") | Y20: =IF(AND($L20="",$N20="",$P20=""),"",ROUND((IF($L20="",0,IF($L20<=Einstellungen!$B$16,100,IF($L20<=Einstellungen!$C$16,80+(100-80)*(Einstellungen!$C$16-$L20)/(Einstellungen!$C$16-Einstellungen!$B$16),IF($L20<=Einstellungen!$D$16,80*(Einstellungen!$D$16-$L20)/(Einstellungen!$D$16-Einstellungen!$C$16),0))))*Einstellungen!$E$16+IF($N20="",0,IF($N20<=Einstellungen!$B$17,100,IF($N20<=Einstellungen!$C$17,80+(100-80)*(Einstellungen!$C$17-$N20)/(Einstellungen!$C$17-Einstellungen!$B$17),IF($N20<=Einstellungen!$D$17,80*(Einstellungen!$D$17-$N20)/(Einstellungen!$D$17-Einstellungen!$C$17),0))))*Einstellungen!$E$17+IF($P20="",0,IF($P20<=Einstellungen!$B$18,100,IF($P20<=Einstellungen!$C$18,80+(100-80)*(Einstellungen!$C$18-$P20)/(Einstellungen!$C$18-Einstellungen!$B$18),IF($P20<=Einstellungen!$D$18,80*(Einstellungen!$D$18-$P20)/(Einstellungen!$D$18-Einstellungen!$C$18),0))))*Einstellungen!$E$18)/(Einstellungen!$E$16+Einstellungen!$E$17+Einstellungen!$E$18),0)) | Z20: =IF(AND($E20="",$D20="",$G20="",$V20="",$Q20="",$T20="",$W20="",$U20=""),"",ROUND(IF($E20="",0,IF($E20<Einstellungen!$B$21,0,IF($E20>=Einstellungen!$B$22,100,($E20-Einstellungen!$B$21)/(Einstellungen!$B$22-Einstellungen!$B$21)*100)))/100*Einstellungen!$B$5+IF($W20="",0,$W20/100)*Einstellungen!$B$6+(IF($G20="",0,MAX(0,MIN(100,($G20-Einstellungen!$B$25)/(Einstellungen!$B$26-Einstellungen!$B$25)*100)))+IF($I20="",0,MAX(0,MIN(100,($I20-Einstellungen!$B$27)/(Einstellungen!$B$28-Einstellungen!$B$27)*100))))/2/100*Einstellungen!$B$7+IF($V20="",0,$V20/100)*Einstellungen!$B$8+IF($R20="",0,MAX(0,MIN(100,(Einstellungen!$B$32-$R20)/(Einstellungen!$B$32-Einstellungen!$B$31)*100)))/100*Einstellungen!$B$9+IF($D20="",0,$D20/5*100)/100*Einstellungen!$B$10+IF($AD20="",0,$AD20)/100*Einstellungen!$B$11+IF($U20="",0,$U20/5*100)/100*Einstellungen!$B$12,0)) | AA20: =IF($X20="","",$X20*1000000000000+IF($G20="",0,$G20)*1000000+IF($H20="",0,$H20)*1000+IF($I20="",0,$I20)+IF($N20="",0,MAX(0,1000-$N20))/1000+IF($A20="",0,$A20)/1000000) | AB20: =IF($Y20="","",_xludf.RANK.EQ($Y20,$Y$2:$Y$201,0))
T21: =IFERROR(IF($Q21="","",$Q21/$H21),"") | U21: =IFERROR(IF($Q21="","",$Q21/$G21),"") | Y21: =IF(AND($L21="",$N21="",$P21=""),"",ROUND((IF($L21="",0,IF($L21<=Einstellungen!$B$16,100,IF($L21<=Einstellungen!$C$16,80+(100-80)*(Einstellungen!$C$16-$L21)/(Einstellungen!$C$16-Einstellungen!$B$16),IF($L21<=Einstellungen!$D$16,80*(Einstellungen!$D$16-$L21)/(Einstellungen!$D$16-Einstellungen!$C$16),0))))*Einstellungen!$E$16+IF($N21="",0,IF($N21<=Einstellungen!$B$17,100,IF($N21<=Einstellungen!$C$17,80+(100-80)*(Einstellungen!$C$17-$N21)/(Einstellungen!$C$17-Einstellungen!$B$17),IF($N21<=Einstellungen!$D$17,80*(Einstellungen!$D$17-$N21)/(Einstellungen!$D$17-Einstellungen!$C$17),0))))*Einstellungen!$E$17+IF($P21="",0,IF($P21<=Einstellungen!$B$18,100,IF($P21<=Einstellungen!$C$18,80+(100-80)*(Einstellungen!$C$18-$P21)/(Einstellungen!$C$18-Einstellungen!$B$18),IF($P21<=Einstellungen!$D$18,80*(Einstellungen!$D$18-$P21)/(Einstellungen!$D$18-Einstellungen!$C$18),0))))*Einstellungen!$E$18)/(Einstellungen!$E$16+Einstellungen!$E$17+Einstellungen!$E$18),0)) | Z21: =IF(AND($E21="",$D21="",$G21="",$V21="",$Q21="",$T21="",$W21="",$U21=""),"",ROUND(IF($E21="",0,IF($E21<Einstellungen!$B$21,0,IF($E21>=Einstellungen!$B$22,100,($E21-Einstellungen!$B$21)/(Einstellungen!$B$22-Einstellungen!$B$21)*100)))/100*Einstellungen!$B$5+IF($W21="",0,$W21/100)*Einstellungen!$B$6+(IF($G21="",0,MAX(0,MIN(100,($G21-Einstellungen!$B$25)/(Einstellungen!$B$26-Einstellungen!$B$25)*100)))+IF($I21="",0,MAX(0,MIN(100,($I21-Einstellungen!$B$27)/(Einstellungen!$B$28-Einstellungen!$B$27)*100))))/2/100*Einstellungen!$B$7+IF($V21="",0,$V21/100)*Einstellungen!$B$8+IF($R21="",0,MAX(0,MIN(100,(Einstellungen!$B$32-$R21)/(Einstellungen!$B$32-Einstellungen!$B$31)*100)))/100*Einstellungen!$B$9+IF($D21="",0,$D21/5*100)/100*Einstellungen!$B$10+IF($AD21="",0,$AD21)/100*Einstellungen!$B$11+IF($U21="",0,$U21/5*100)/100*Einstellungen!$B$12,0)) | AA21: =IF($X21="","",$X21*1000000000000+IF($G21="",0,$G21)*1000000+IF($H21="",0,$H21)*1000+IF($I21="",0,$I21)+IF($N21="",0,MAX(0,1000-$N21))/1000+IF($A21="",0,$A21)/1000000) | AB21: =IF($Y21="","",_xludf.RANK.EQ($Y21,$Y$2:$Y$201,0))
T22: =IFERROR(IF($Q22="","",$Q22/$H22),"") | U22: =IFERROR(IF($Q22="","",$Q22/$G22),"") | Y22: =IF(AND($L22="",$N22="",$P22=""),"",ROUND((IF($L22="",0,IF($L22<=Einstellungen!$B$16,100,IF($L22<=Einstellungen!$C$16,80+(100-80)*(Einstellungen!$C$16-$L22)/(Einstellungen!$C$16-Einstellungen!$B$16),IF($L22<=Einstellungen!$D$16,80*(Einstellungen!$D$16-$L22)/(Einstellungen!$D$16-Einstellungen!$C$16),0))))*Einstellungen!$E$16+IF($N22="",0,IF($N22<=Einstellungen!$B$17,100,IF($N22<=Einstellungen!$C$17,80+(100-80)*(Einstellungen!$C$17-$N22)/(Einstellungen!$C$17-Einstellungen!$B$17),IF($N22<=Einstellungen!$D$17,80*(Einstellungen!$D$17-$N22)/(Einstellungen!$D$17-Einstellungen!$C$17),0))))*Einstellungen!$E$17+IF($P22="",0,IF($P22<=Einstellungen!$B$18,100,IF($P22<=Einstellungen!$C$18,80+(100-80)*(Einstellungen!$C$18-$P22)/(Einstellungen!$C$18-Einstellungen!$B$18),IF($P22<=Einstellungen!$D$18,80*(Einstellungen!$D$18-$P22)/(Einstellungen!$D$18-Einstellungen!$C$18),0))))*Einstellungen!$E$18)/(Einstellungen!$E$16+Einstellungen!$E$17+Einstellungen!$E$18),0)) | Z22: =IF(AND($E22="",$D22="",$G22="",$V22="",$Q22="",$T22="",$W22="",$U22=""),"",ROUND(IF($E22="",0,IF($E22<Einstellungen!$B$21,0,IF($E22>=Einstellungen!$B$22,100,($E22-Einstellungen!$B$21)/(Einstellungen!$B$22-Einstellungen!$B$21)*100)))/100*Einstellungen!$B$5+IF($W22="",0,$W22/100)*Einstellungen!$B$6+(IF($G22="",0,MAX(0,MIN(100,($G22-Einstellungen!$B$25)/(Einstellungen!$B$26-Einstellungen!$B$25)*100)))+IF($I22="",0,MAX(0,MIN(100,($I22-Einstellungen!$B$27)/(Einstellungen!$B$28-Einstellungen!$B$27)*100))))/2/100*Einstellungen!$B$7+IF($V22="",0,$V22/100)*Einstellungen!$B$8+IF($R22="",0,MAX(0,MIN(100,(Einstellungen!$B$32-$R22)/(Einstellungen!$B$32-Einstellungen!$B$31)*100)))/100*Einstellungen!$B$9+IF($D22="",0,$D22/5*100)/100*Einstellungen!$B$10+IF($AD22="",0,$AD22)/100*Einstellungen!$B$11+IF($U22="",0,$U22/5*100)/100*Einstellungen!$B$12,0)) | AA22: =IF($X22="","",$X22*1000000000000+IF($G22="",0,$G22)*1000000+IF($H22="",0,$H22)*1000+IF($I22="",0,$I22)+IF($N22="",0,MAX(0,1000-$N22))/1000+IF($A22="",0,$A22)/1000000) | AB22: =IF($Y22="","",_xludf.RANK.EQ($Y22,$Y$2:$Y$201,0))
T23: =IFERROR(IF($Q23="","",$Q23/$H23),"") | U23: =IFERROR(IF($Q23="","",$Q23/$G23),"") | Y23: =IF(AND($L23="",$N23="",$P23=""),"",ROUND((IF($L23="",0,IF($L23<=Einstellungen!$B$16,100,IF($L23<=Einstellungen!$C$16,80+(100-80)*(Einstellungen!$C$16-$L23)/(Einstellungen!$C$16-Einstellungen!$B$16),IF($L23<=Einstellungen!$D$16,80*(Einstellungen!$D$16-$L23)/(Einstellungen!$D$16-Einstellungen!$C$16),0))))*Einstellungen!$E$16+IF($N23="",0,IF($N23<=Einstellungen!$B$17,100,IF($N23<=Einstellungen!$C$17,80+(100-80)*(Einstellungen!$C$17-$N23)/(Einstellungen!$C$17-Einstellungen!$B$17),IF($N23<=Einstellungen!$D$17,80*(Einstellungen!$D$17-$N23)/(Einstellungen!$D$17-Einstellungen!$C$17),0))))*Einstellungen!$E$17+IF($P23="",0,IF($P23<=Einstellungen!$B$18,100,IF($P23<=Einstellungen!$C$18,80+(100-80)*(Einstellungen!$C$18-$P23)/(Einstellungen!$C$18-Einstellungen!$B$18),IF($P23<=Einstellungen!$D$18,80*(Einstellungen!$D$18-$P23)/(Einstellungen!$D$18-Einstellungen!$C$18),0))))*Einstellungen!$E$18)/(Einstellungen!$E$16+Einstellungen!$E$17+Einstellungen!$E$18),0)) | Z23: =IF(AND($E23="",$D23="",$G23="",$V23="",$Q23="",$T23="",$W23="",$U23=""),"",ROUND(IF($E23="",0,IF($E23<Einstellungen!$B$21,0,IF($E23>=Einstellungen!$B$22,100,($E23-Einstellungen!$B$21)/(Einstellungen!$B$22-Einstellungen!$B$21)*100)))/100*Einstellungen!$B$5+IF($W23="",0,$W23/100)*Einstellungen!$B$6+(IF($G23="",0,MAX(0,MIN(100,($G23-Einstellungen!$B$25)/(Einstellungen!$B$26-Einstellungen!$B$25)*100)))+IF($I23="",0,MAX(0,MIN(100,($I23-Einstellungen!$B$27)/(Einstellungen!$B$28-Einstellungen!$B$27)*100))))/2/100*Einstellungen!$B$7+IF($V23="",0,$V23/100)*Einstellungen!$B$8+IF($R23="",0,MAX(0,MIN(100,(Einstellungen!$B$32-$R23)/(Einstellungen!$B$32-Einstellungen!$B$31)*100)))/100*Einstellungen!$B$9+IF($D23="",0,$D23/5*100)/100*Einstellungen!$B$10+IF($AD23="",0,$AD23)/100*Einstellungen!$B$11+IF($U23="",0,$U23/5*100)/100*Einstellungen!$B$12,0)) | AA23: =IF($X23="","",$X23*1000000000000+IF($G23="",0,$G23)*1000000+IF($H23="",0,$H23)*1000+IF($I23="",0,$I23)+IF($N23="",0,MAX(0,1000-$N23))/1000+IF($A23="",0,$A23)/1000000) | AB23: =IF($Y23="","",_xludf.RANK.EQ($Y23,$Y$2:$Y$201,0))
T24: =IFERROR(IF($Q24="","",$Q24/$H24),"") | U24: =IFERROR(IF($Q24="","",$Q24/$G24),"") | Y24: =IF(AND($L24="",$N24="",$P24=""),"",ROUND((IF($L24="",0,IF($L24<=Einstellungen!$B$16,100,IF($L24<=Einstellungen!$C$16,80+(100-80)*(Einstellungen!$C$16-$L24)/(Einstellungen!$C$16-Einstellungen!$B$16),IF($L24<=Einstellungen!$D$16,80*(Einstellungen!$D$16-$L24)/(Einstellungen!$D$16-Einstellungen!$C$16),0))))*Einstellungen!$E$16+IF($N24="",0,IF($N24<=Einstellungen!$B$17,100,IF($N24<=Einstellungen!$C$17,80+(100-80)*(Einstellungen!$C$17-$N24)/(Einstellungen!$C$17-Einstellungen!$B$17),IF($N24<=Einstellungen!$D$17,80*(Einstellungen!$D$17-$N24)/(Einstellungen!$D$17-Einstellungen!$C$17),0))))*Einstellungen!$E$17+IF($P24="",0,IF($P24<=Einstellungen!$B$18,100,IF($P24<=Einstellungen!$C$18,80+(100-80)*(Einstellungen!$C$18-$P24)/(Einstellungen!$C$18-Einstellungen!$B$18),IF($P24<=Einstellungen!$D$18,80*(Einstellungen!$D$18-$P24)/(Einstellungen!$D$18-Einstellungen!$C$18),0))))*Einstellungen!$E$18)/(Einstellungen!$E$16+Einstellungen!$E$17+Einstellungen!$E$18),0)) | Z24: =IF(AND($E24="",$D24="",$G24="",$V24="",$Q24="",$T24="",$W24="",$U24=""),"",ROUND(IF($E24="",0,IF($E24<Einstellungen!$B$21,0,IF($E24>=Einstellungen!$B$22,100,($E24-Einstellungen!$B$21)/(Einstellungen!$B$22-Einstellungen!$B$21)*100)))/100*Einstellungen!$B$5+IF($W24="",0,$W24/100)*Einstellungen!$B$6+(IF($G24="",0,MAX(0,MIN(100,($G24-Einstellungen!$B$25)/(Einstellungen!$B$26-Einstellungen!$B$25)*100)))+IF($I24="",0,MAX(0,MIN(100,($I24-Einstellungen!$B$27)/(Einstellungen!$B$28-Einstellungen!$B$27)*100))))/2/100*Einstellungen!$B$7+IF($V24="",0,$V24/100)*Einstellungen!$B$8+IF($R24="",0,MAX(0,MIN(100,(Einstellungen!$B$32-$R24)/(Einstellungen!$B$32-Einstellungen!$B$31)*100)))/100*Einstellungen!$B$9+IF($D24="",0,$D24/5*100)/100*Einstellungen!$B$10+IF($AD24="",0,$AD24)/100*Einstellungen!$B$11+IF($U24="",0,$U24/5*100)/100*Einstellungen!$B$12,0)) | AA24: =IF($X24="","",$X24*1000000000000+IF($G24="",0,$G24)*1000000+IF($H24="",0,$H24)*1000+IF($I24="",0,$I24)+IF($N24="",0,MAX(0,1000-$N24))/1000+IF($A24="",0,$A24)/1000000) | AB24: =IF($Y24="","",_xludf.RANK.EQ($Y24,$Y$2:$Y$201,0))
T25: =IFERROR(IF($Q25="","",$Q25/$H25),"") | U25: =IFERROR(IF($Q25="","",$Q25/$G25),"") | Y25: =IF(AND($L25="",$N25="",$P25=""),"",ROUND((IF($L25="",0,IF($L25<=Einstellungen!$B$16,100,IF($L25<=Einstellungen!$C$16,80+(100-80)*(Einstellungen!$C$16-$L25)/(Einstellungen!$C$16-Einstellungen!$B$16),IF($L25<=Einstellungen!$D$16,80*(Einstellungen!$D$16-$L25)/(Einstellungen!$D$16-Einstellungen!$C$16),0))))*Einstellungen!$E$16+IF($N25="",0,IF($N25<=Einstellungen!$B$17,100,IF($N25<=Einstellungen!$C$17,80+(100-80)*(Einstellungen!$C$17-$N25)/(Einstellungen!$C$17-Einstellungen!$B$17),IF($N25<=Einstellungen!$D$17,80*(Einstellungen!$D$17-$N25)/(Einstellungen!$D$17-Einstellungen!$C$17),0))))*Einstellungen!$E$17+IF($P25="",0,IF($P25<=Einstellungen!$B$18,100,IF($P25<=Einstellungen!$C$18,80+(100-80)*(Einstellungen!$C$18-$P25)/(Einstellungen!$C$18-Einstellungen!$B$18),IF($P25<=Einstellungen!$D$18,80*(Einstellungen!$D$18-$P25)/(Einstellungen!$D$18-Einstellungen!$C$18),0))))*Einstellungen!$E$18)/(Einstellungen!$E$16+Einstellungen!$E$17+Einstellungen!$E$18),0)) | Z25: =IF(AND($E25="",$D25="",$G25="",$V25="",$Q25="",$T25="",$W25="",$U25=""),"",ROUND(IF($E25="",0,IF($E25<Einstellungen!$B$21,0,IF($E25>=Einstellungen!$B$22,100,($E25-Einstellungen!$B$21)/(Einstellungen!$B$22-Einstellungen!$B$21)*100)))/100*Einstellungen!$B$5+IF($W25="",0,$W25/100)*Einstellungen!$B$6+(IF($G25="",0,MAX(0,MIN(100,($G25-Einstellungen!$B$25)/(Einstellungen!$B$26-Einstellungen!$B$25)*100)))+IF($I25="",0,MAX(0,MIN(100,($I25-Einstellungen!$B$27)/(Einstellungen!$B$28-Einstellungen!$B$27)*100))))/2/100*Einstellungen!$B$7+IF($V25="",0,$V25/100)*Einstellungen!$B$8+IF($R25="",0,MAX(0,MIN(100,(Einstellungen!$B$32-$R25)/(Einstellungen!$B$32-Einstellungen!$B$31)*100)))/100*Einstellungen!$B$9+IF($D25="",0,$D25/5*100)/100*Einstellungen!$B$10+IF($AD25="",0,$AD25)/100*Einstellungen!$B$11+IF($U25="",0,$U25/5*100)/100*Einstellungen!$B$12,0)) | AA25: =IF($X25="","",$X25*1000000000000+IF($G25="",0,$G25)*1000000+IF($H25="",0,$H25)*1000+IF($I25="",0,$I25)+IF($N25="",0,MAX(0,1000-$N25))/1000+IF($A25="",0,$A25)/1000000) | AB25: =IF($Y25="","",_xludf.RANK.EQ($Y25,$Y$2:$Y$201,0))
T26: =IFERROR(IF($Q26="","",$Q26/$H26),"") | U26: =IFERROR(IF($Q26="","",$Q26/$G26),"") | Y26: =IF(AND($L26="",$N26="",$P26=""),"",ROUND((IF($L26="",0,IF($L26<=Einstellungen!$B$16,100,IF($L26<=Einstellungen!$C$16,80+(100-80)*(Einstellungen!$C$16-$L26)/(Einstellungen!$C$16-Einstellungen!$B$16),IF($L26<=Einstellungen!$D$16,80*(Einstellungen!$D$16-$L26)/(Einstellungen!$D$16-Einstellungen!$C$16),0))))*Einstellungen!$E$16+IF($N26="",0,IF($N26<=Einstellungen!$B$17,100,IF($N26<=Einstellungen!$C$17,80+(100-80)*(Einstellungen!$C$17-$N26)/(Einstellungen!$C$17-Einstellungen!$B$17),IF($N26<=Einstellungen!$D$17,80*(Einstellungen!$D$17-$N26)/(Einstellungen!$D$17-Einstellungen!$C$17),0))))*Einstellungen!$E$17+IF($P26="",0,IF($P26<=Einstellungen!$B$18,100,IF($P26<=Einstellungen!$C$18,80+(100-80)*(Einstellungen!$C$18-$P26)/(Einstellungen!$C$18-Einstellungen!$B$18),IF($P26<=Einstellungen!$D$18,80*(Einstellungen!$D$18-$P26)/(Einstellungen!$D$18-Einstellungen!$C$18),0))))*Einstellungen!$E$18)/(Einstellungen!$E$16+Einstellungen!$E$17+Einstellungen!$E$18),0)) | Z26: =IF(AND($E26="",$D26="",$G26="",$V26="",$Q26="",$T26="",$W26="",$U26=""),"",ROUND(IF($E26="",0,IF($E26<Einstellungen!$B$21,0,IF($E26>=Einstellungen!$B$22,100,($E26-Einstellungen!$B$21)/(Einstellungen!$B$22-Einstellungen!$B$21)*100)))/100*Einstellungen!$B$5+IF($W26="",0,$W26/100)*Einstellungen!$B$6+(IF($G26="",0,MAX(0,MIN(100,($G26-Einstellungen!$B$25)/(Einstellungen!$B$26-Einstellungen!$B$25)*100)))+IF($I26="",0,MAX(0,MIN(100,($I26-Einstellungen!$B$27)/(Einstellungen!$B$28-Einstellungen!$B$27)*100))))/2/100*Einstellungen!$B$7+IF($V26="",0,$V26/100)*Einstellungen!$B$8+IF($R26="",0,MAX(0,MIN(100,(Einstellungen!$B$32-$R26)/(Einstellungen!$B$32-Einstellungen!$B$31)*100)))/100*Einstellungen!$B$9+IF($D26="",0,$D26/5*100)/100*Einstellungen!$B$10+IF($AD26="",0,$AD26)/100*Einstellungen!$B$11+IF($U26="",0,$U26/5*100)/100*Einstellungen!$B$12,0)) | AA26: =IF($X26="","",$X26*1000000000000+IF($G26="",0,$G26)*1000000+IF($H26="",0,$H26)*1000+IF($I26="",0,$I26)+IF($N26="",0,MAX(0,1000-$N26))/1000+IF($A26="",0,$A26)/1000000) | AB26: =IF($Y26="","",_xludf.RANK.EQ($Y26,$Y$2:$Y$201,0))
T27: =IFERROR(IF($Q27="","",$Q27/$H27),"") | U27: =IFERROR(IF($Q27="","",$Q27/$G27),"") | Y27: =IF(AND($L27="",$N27="",$P27=""),"",ROUND((IF($L27="",0,IF($L27<=Einstellungen!$B$16,100,IF($L27<=Einstellungen!$C$16,80+(100-80)*(Einstellungen!$C$16-$L27)/(Einstellungen!$C$16-Einstellungen!$B$16),IF($L27<=Einstellungen!$D$16,80*(Einstellungen!$D$16-$L27)/(Einstellungen!$D$16-Einstellungen!$C$16),0))))*Einstellungen!$E$16+IF($N27="",0,IF($N27<=Einstellungen!$B$17,100,IF($N27<=Einstellungen!$C$17,80+(100-80)*(Einstellungen!$C$17-$N27)/(Einstellungen!$C$17-Einstellungen!$B$17),IF($N27<=Einstellungen!$D$17,80*(Einstellungen!$D$17-$N27)/(Einstellungen!$D$17-Einstellungen!$C$17),0))))*Einstellungen!$E$17+IF($P27="",0,IF($P27<=Einstellungen!$B$18,100,IF($P27<=Einstellungen!$C$18,80+(100-80)*(Einstellungen!$C$18-$P27)/(Einstellungen!$C$18-Einstellungen!$B$18),IF($P27<=Einstellungen!$D$18,80*(Einstellungen!$D$18-$P27)/(Einstellungen!$D$18-Einstellungen!$C$18),0))))*Einstellungen!$E$18)/(Einstellungen!$E$16+Einstellungen!$E$17+Einstellungen!$E$18),0)) | Z27: =IF(AND($E27="",$D27="",$G27="",$V27="",$Q27="",$T27="",$W27="",$U27=""),"",ROUND(IF($E27="",0,IF($E27<Einstellungen!$B$21,0,IF($E27>=Einstellungen!$B$22,100,($E27-Einstellungen!$B$21)/(Einstellungen!$B$22-Einstellungen!$B$21)*100)))/100*Einstellungen!$B$5+IF($W27="",0,$W27/100)*Einstellungen!$B$6+(IF($G27="",0,MAX(0,MIN(100,($G27-Einstellungen!$B$25)/(Einstellungen!$B$26-Einstellungen!$B$25)*100)))+IF($I27="",0,MAX(0,MIN(100,($I27-Einstellungen!$B$27)/(Einstellungen!$B$28-Einstellungen!$B$27)*100))))/2/100*Einstellungen!$B$7+IF($V27="",0,$V27/100)*Einstellungen!$B$8+IF($R27="",0,MAX(0,MIN(100,(Einstellungen!$B$32-$R27)/(Einstellungen!$B$32-Einstellungen!$B$31)*100)))/100*Einstellungen!$B$9+IF($D27="",0,$D27/5*100)/100*Einstellungen!$B$10+IF($AD27="",0,$AD27)/100*Einstellungen!$B$11+IF($U27="",0,$U27/5*100)/100*Einstellungen!$B$12,0)) | AA27: =IF($X27="","",$X27*1000000000000+IF($G27="",0,$G27)*1000000+IF($H27="",0,$H27)*1000+IF($I27="",0,$I27)+IF($N27="",0,MAX(0,1000-$N27))/1000+IF($A27="",0,$A27)/1000000) | AB27: =IF($Y27="","",_xludf.RANK.EQ($Y27,$Y$2:$Y$201,0))
... T201: =IFERROR(IF($Q201="","",$Q201/$H201),"") | U201: =IFERROR(IF($Q201="","",$Q201/$G201),"") | Y201: =IF(AND($L201="",$N201="",$P201=""),"",ROUND((IF($L201="",0,IF($L201<=Einstellungen!$B$16,100,IF($L201<=Einstellungen!$C$16,80+(100-80)*(Einstellungen!$C$16-$L201)/(Einstellungen!$C$16-Einstellungen!$B$16),IF($L201<=Einstellungen!$D$16,80*(Einstellungen!$D$16-$L201)/(Einstellungen!$D$16-Einstellungen!$C$16),0))))*Einstellungen!$E$16+IF($N201="",0,IF($N201<=Einstellungen!$B$17,100,IF($N201<=Einstellungen!$C$17,80+(100-80)*(Einstellungen!$C$17-$N201)/(Einstellungen!$C$17-Einstellungen!$B$17),IF($N201<=Einstellungen!$D$17,80*(Einstellungen!$D$17-$N201)/(Einstellungen!$D$17-Einstellungen!$C$17),0))))*Einstellungen!$E$17+IF($P201="",0,IF($P201<=Einstellungen!$B$18,100,IF($P201<=Einstellungen!$C$18,80+(100-80)*(Einstellungen!$C$18-$P201)/(Einstellungen!$C$18-Einstellungen!$B$18),IF($P201<=Einstellungen!$D$18,80*(Einstellungen!$D$18-$P201)/(Einstellungen!$D$18-Einstellungen!$C$18),0))))*Einstellungen!$E$18)/(Einstellungen!$E$16+Einstellungen!$E$17+Einstellungen!$E$18),0)) | Z201: =IF(AND($E201="",$D201="",$G201="",$V201="",$Q201="",$T201="",$W201="",$U201=""),"",ROUND(IF($E201="",0,IF($E201<Einstellungen!$B$21,0,IF($E201>=Einstellungen!$B$22,100,($E201-Einstellungen!$B$21)/(Einstellungen!$B$22-Einstellungen!$B$21)*100)))/100*Einstellungen!$B$5+IF($W201="",0,$W201/100)*Einstellungen!$B$6+(IF($G201="",0,MAX(0,MIN(100,($G201-Einstellungen!$B$25)/(Einstellungen!$B$26-Einstellungen!$B$25)*100)))+IF($I201="",0,MAX(0,MIN(100,($I201-Einstellungen!$B$27)/(Einstellungen!$B$28-Einstellungen!$B$27)*100))))/2/100*Einstellungen!$B$7+IF($V201="",0,$V201/100)*Einstellungen!$B$8+IF($R201="",0,MAX(0,MIN(100,(Einstellungen!$B$32-$R201)/(Einstellungen!$B$32-Einstellungen!$B$31)*100)))/100*Einstellungen!$B$9+IF($D201="",0,$D201/5*100)/100*Einstellungen!$B$10+IF($AD201="",0,$AD201)/100*Einstellungen!$B$11+IF($U201="",0,$U201/5*100)/100*Einstellungen!$B$12,0)) | AA201: =IF($X201="","",$X201*1000000000000+IF($G201="",0,$G201)*1000000+IF($H201="",0,$H201)*1000+IF($I201="",0,$I201)+IF($N201="",0,MAX(0,1000-$N201))/1000+IF($A201="",0,$A201)/1000000) | AB201: =IF($Y201="","",_xludf.RANK.EQ($Y201,$Y$2:$Y$201,0))
A202: 15 | B202: Apartment in Portals Nous, Mallorca | C202: https://www.kyero.com/en/property/17828907-apartment-for-sale-portals-nous?prime_boost_id=17828907 | E202: 3 | J202: Portals Nous | K202: 23.8 | L202: 23 | M202: 66.6 | N202: 56 | O202: 21.8 | P202: 22 | Q202: 64.3 | R202: 52 | S202: 3500000 | AH202: Quelle: Kyero
A203: 16 | B203: Country house in Felanitx, Mallorca | C203: https://www.kyero.com/en/property/18737859-country-house-for-sale-felanitx?prime_boost_id=18737859 | E203: 4 | G203: 23160 | J203: Felanitx | K203: 45 | L203: 40 | M203: 26.8 | N203: 30 | O203: 83.2 | P203: 68 | Q203: 24.5 | R203: 26 | S203: 2435000 | U203: 105 | AH203: Quelle: Kyero
A204: 17 | B204: Villa in Santa Ponsa, Mallorca | C204: https://www.kyero.com/en/property/19926319-villa-for-sale-santa-ponsa?prime_boost_id=19926319 | E204: 4 | G204: 1448 | J204: Santa Ponsa | K204: 31.1 | L204: 28 | M204: 73.9 | N204: 61 | O204: 15.2 | P204: 19 | Q204: 71.6 | R204: 57 | S204: 3900000 | U204: 2693 | AH204: Quelle: Kyero
A205: 18 | B205: Country house in Colonia De Sant Pere, Mallorca | C205: https://www.kyero.com/en/property/19956683-country-house-for-sale-colonia-de-sant-pere | E205: 6 | G205: 14200 | J205: Mallorca | K205: 47.4 | L205: 40 | M205: 51.8 | N205: 55 | O205: 70 | P205: 56 | Q205: 49.5 | R205: 51 | S205: 2350000 | U205: 165 | AH205: Quelle: Kyero
A206: 19 | B206: Villa in Bendinat, Mallorca | C206: https://www.kyero.com/en/property/18538834-villa-for-sale-bendinat | E206: 4 | G206: 753 | J206: Bendinat | K206: 23.1 | L206: 22 | M206: 65.8 | N206: 55 | O206: 23.2 | P206: 23 | Q206: 63.5 | R206: 51 | S206: 3100000 | U206: 4117 | AH206: Quelle: Kyero
A207: 20 | B207: Villa in Cala Murada, Mallorca | C207: https://www.kyero.com/en/property/18605783-villa-for-sale-cala-murada | E207: 6 | G207: 1650 | J207: Mallorca | K207: 47.4 | L207: 40 | M207: 51.8 | N207: 55 | O207: 70 | P207: 56 | Q207: 49.5 | R207: 51 | S207: 2790000 | U207: 1691 | AH207: Quelle: Kyero
A208: 21 | B208: Country house in Santa Maria Del Cami, Mallorca | C208: https://www.kyero.com/en/property/20534135-country-house-for-sale-santa-maria-del-cami | E208: 7 | G208: 13500 | J208: Mallorca | K208: 47.4 | L208: 40 | M208: 51.8 | N208: 55 | O208: 70 | P208: 56 | Q208: 49.5 | R208: 51 | S208: 3000000 | U208: 222 | AH208: Quelle: Kyero
A209: 22 | B209: Country house in Llubi, Mallorca | C209: https://www.kyero.com/en/property/20467885-country-house-for-sale-llubi | E209: 4 | G209: 15000 | J209: Mallorca | K209: 47.4 | L209: 40 | M209: 51.8 | N209: 55 | O209: 70 | P209: 56 | Q209: 49.5 | R209: 51 | S209: 2750000 | U209: 183 | AH209: Quelle: Kyero
A210: 23 | B210: Finca in Campos, Mallorca | C210: https://www.kyero.com/en/property/20520519-country-house-for-sale-campos | E210: 6 | G210: 14200 | J210: Mallorca | K210: 47.4 | L210: 40 | M210: 51.8 | N210: 55 | O210: 70 | P210: 56 | Q210: 49.5 | R210: 51 | S210: 3650000 | U210: 257 | AH210: Quelle: Kyero
A211: 24 | B211: Country house in Sant Llorenc Des Cardassar, Mallorca | C211: https://www.kyero.com/en/property/20510970-country-house-for-sale-sant-llorenc-des-cardassar | E211: 4 | G211: 17545 | J211: Mallorca | K211: 47.4 | L211: 40 | M211: 51.8 | N211: 55 | O211: 70 | P211: 56 | Q211: 49.5 | R211: 51 | S211: 2690000 | U211: 153 | AH211: Quelle: Kyero
A212: 25 | B212: Remote viewing available | C212: https://www.kyero.com/en/property/20539651-apartment-for-sale-palma-de-mallorca | E212: 3 | J212: Palma | K212: 9.7 | L212: 14 | M212: 52.5 | N212: 47 | O212: 32.1 | P212: 36 | Q212: 50.2 | R212: 44 | S212: 3250000 | AH212: Quelle: Kyero
A213: 26 | B213: Country house in Binissalem, Mallorca | C213: https://www.kyero.com/en/property/20533859-country-house-for-sale-binissalem | E213: 8 | G213: 15000 | J213: Mallorca | K213: 47.4 | L213: 40 | M213: 51.8 | N213: 55 | O213: 70 | P213: 56 | Q213: 49.5 | R213: 51 | S213: 3400000 | U213: 227 | AH213: Quelle: Kyero
A214: 27 | B214: Remote viewing available | C214: https://www.kyero.com/en/property/19754127-apartment-for-sale-peguera | E214: 3 | J214: Peguera | K214: 35.3 | L214: 30 | M214: 78 | N214: 63 | O214: 9.1 | P214: 14 | Q214: 75.7 | R214: 60 | S214: 2750000 | AH214: Quelle: Kyero
A215: 28 | B215: Villa in Nova Santa Ponsa, Mallorca | C215: https://www.kyero.com/en/property/20536451-villa-for-sale-nova-santa-ponsa | E215: 5 | G215: 1260 | J215: Santa Ponsa | K215: 31.1 | L215: 28 | M215: 73.9 | N215: 61 | O215: 15.2 | P215: 19 | Q215: 71.6 | R215: 57 | S215: 2390000 | U215: 1897 | AH215: Quelle: Kyero
A216: 29 | B216: Villa in Sol De Mallorca, Mallorca | C216: https://www.kyero.com/en/property/20524264-villa-for-sale-sol-de-mallorca | E216: 5 | G216: 1226 | J216: Mallorca | K216: 47.4 | L216: 40 | M216: 51.8 | N216: 55 | O216: 70 | P216: 56 | Q216: 49.5 | R216: 51 | S216: 2350000 | U216: 1917 | AH216: Quelle: Kyero
A217: 30 | B217: Villa in Calvia, Mallorca | C217: https://www.kyero.com/en/property/20468266-villa-for-sale-calvia | G217: 1434 | J217: Mallorca | K217: 47.4 | L217: 40 | M217: 51.8 | N217: 55 | O217: 70 | P217: 56 | Q217: 49.5 | R217: 51 | S217: 2975000 | U217: 2075 | AH217: Quelle: Kyero
A218: 31 | B218: Villa in Bendinat, Mallorca | C218: https://www.kyero.com/en/property/20496393-villa-for-sale-bendinat | E218: 4 | G218: 454 | J218: Bendinat | K218: 23.1 | L218: 22 | M218: 65.8 | N218: 55 | O218: 23.2 | P218: 23 | Q218: 63.5 | R218: 51 | S218: 6200000 | U218: 13656 | AH218: Quelle: Kyero
A219: 32 | B219: Villa in Palma De Mallorca, Mallorca | C219: https://www.kyero.com/en/property/19851775-villa-for-sale-palma-de-mallorca | E219: 5 | G219: 360 | J219: Palma | K219: 9.7 | L219: 14 | M219: 52.5 | N219: 47 | O219: 32.1 | P219: 36 | Q219: 50.2 | R219: 44 | S219: 3450000 | U219: 9583 | AH219: Quelle: Kyero
A220: 33 | B220: Finca in Felanitx, Mallorca | C220: https://www.kyero.com/en/property/19765507-country-house-for-sale-felanitx | E220: 6 | G220: 28000 | J220: Mallorca | K220: 47.4 | L220: 40 | M220: 51.8 | N220: 55 | O220: 70 | P220: 56 | Q220: 49.5 | R220: 51 | S220: 5650000 | U220: 202 | AH220: Quelle: Kyero
A221: 34 | B221: Villa in Calvia, Mallorca | C221: https://www.kyero.com/en/property/20468252-villa-for-sale-calvia | E221: 4 | G221: 1150 | J221: Mallorca | K221: 47.4 | L221: 40 | M221: 51.8 | N221: 55 | O221: 70 | P221: 56 | Q221: 49.5 | R221: 51 | S221: 2850000 | U221: 2478 | AH221: Quelle: Kyero
A222: 35 | B222: Country house in Montuiri, Mallorca | C222: https://www.kyero.com/en/property/19175886-country-house-for-sale-montuiri | E222: 5 | G222: 15954 | J222: Mallorca | K222: 47.4 | L222: 40 | M222: 51.8 | N222: 55 | O222: 70 | P222: 56 | Q222: 49.5 | R222: 51 | S222: 5900000 | U222: 370 | AH222: Quelle: Kyero
A223: 36 | B223: Remote viewing available | C223: https://www.kyero.com/en/property/20444466-commercial-property-for-sale-capdepera | E223: 5 | G223: 68834 | J223: Artà | K223: 68.3 | L223: 61 | M223: 63.7 | N223: 64 | O223: 102.5 | P223: 86 | Q223: 61.4 | R223: 61 | S223: 4500000 | U223: 65 | AH223: Quelle: Kyero
A224: 37 | B224: Villa in Nova Santa Ponsa, Mallorca | C224: https://www.kyero.com/en/property/19784098-villa-for-sale-nova-santa-ponsa | E224: 5 | G224: 1090 | J224: Santa Ponsa | K224: 31.1 | L224: 28 | M224: 73.9 | N224: 61 | O224: 15.2 | P224: 19 | Q224: 71.6 | R224: 57 | S224: 2790000 | U224: 2560 | AH224: Quelle: Kyero
A225: 38 | B225: Country house in Andratx, Mallorca | C225: https://www.kyero.com/en/property/14449091-country-house-for-sale-andratx | E225: 5 | G225: 62507 | J225: Andratx | K225: 40.3 | L225: 36 | M225: 83 | N225: 68 | O225: 2.7 | P225: 7 | Q225: 80.7 | R225: 65 | S225: 3995000 | U225: 64 | AH225: Quelle: Kyero
A226: 39 | B226: Villa in Palmanova, Mallorca | C226: https://www.kyero.com/en/property/19784127-villa-for-sale-palmanova | E226: 6 | G226: 1195 | J226: Palma | K226: 9.7 | L226: 14 | M226: 52.5 | N226: 47 | O226: 32.1 | P226: 36 | Q226: 50.2 | R226: 44 | S226: 3950000 | U226: 3305 | AH226: Quelle: Kyero
A227: 40 | B227: Villa in Cala d'Or, Mallorca | C227: https://www.kyero.com/en/property/20507314-villa-for-sale-cala-d-or | E227: 4 | G227: 938 | J227: Mallorca | K227: 47.4 | L227: 40 | M227: 51.8 | N227: 55 | O227: 70 | P227: 56 | Q227: 49.5 | R227: 51 | S227: 2500000 | U227: 2665 | AH227: Quelle: Kyero
A228: 41 | B228: Villa in Puig De Ros, Mallorca | C228: https://www.kyero.com/en/property/19870584-villa-for-sale-puig-de-ros | E228: 5 | G228: 759 | J228: Mallorca | K228: 47.4 | L228: 40 | M228: 51.8 | N228: 55 | O228: 70 | P228: 56 | Q228: 49.5 | R228: 51 | S228: 3600000 | U228: 4743 | AH228: Quelle: Kyero
A229: 42 | B229: Villa in Sol De Mallorca, Mallorca | C229: https://www.kyero.com/en/property/19586343-villa-for-sale-sol-de-mallorca | E229: 4 | G229: 1573 | J229: Mallorca | K229: 47.4 | L229: 40 | M229: 51.8 | N229: 55 | O229: 70 | P229: 56 | Q229: 49.5 | R229: 51 | S229: 3950000 | U229: 2511 | AH229: Quelle: Kyero
A230: 43 | B230: Villa in Badia Blava, Mallorca | C230: https://www.kyero.com/en/property/20325660-villa-for-sale-badia-blava | E230: 5 | G230: 1446 | J230: Palma | K230: 9.7 | L230: 14 | M230: 52.5 | N230: 47 | O230: 32.1 | P230: 36 | Q230: 50.2 | R230: 44 | S230: 3875000 | U230: 2680 | AH230: Quelle: Kyero
A231: 44 | B231: Remote viewing available | C231: https://www.kyero.com/en/property/19326593-apartment-for-sale-santa-ponsa | E231: 2 | J231: Santa Ponsa | K231: 31.1 | L231: 28 | M231: 73.9 | N231: 61 | O231: 15.2 | P231: 19 | Q231: 71.6 | R231: 57 | S231: 2390000 | AH231: Quelle: Kyero
A232: 45 | B232: Villa in Sol De Mallorca, Mallorca | C232: https://www.kyero.com/en/property/19586367-villa-for-sale-sol-de-mallorca | E232: 5 | G232: 1765 | J232: Mallorca | K232: 47.4 | L232: 40 | M232: 51.8 | N232: 55 | O232: 70 | P232: 56 | Q232: 49.5 | R232: 51 | S232: 4600000 | U232: 2606 | AH232: Quelle: Kyero
A233: 46 | B233: Apartment in Portals Nous, Mallorca | C233: https://www.kyero.com/en/property/17845100-apartment-for-sale-portals-nous | E233: 3 | J233: Portals Nous | K233: 23.8 | L233: 23 | M233: 66.6 | N233: 56 | O233: 21.8 | P233: 22 | Q233: 64.3 | R233: 52 | S233: 3350000 | AH233: Quelle: Kyero
A234: 47 | B234: Villa in Calvia, Mallorca | C234: https://www.kyero.com/en/property/19271668-villa-for-sale-calvia | E234: 5 | G234: 828 | J234: Mallorca | K234: 47.4 | L234: 40 | M234: 51.8 | N234: 55 | O234: 70 | P234: 56 | Q234: 49.5 | R234: 51 | S234: 2750000 | U234: 3321 | AH234: Quelle: Kyero
A235: 48 | B235: Country house in Alaro, Mallorca | C235: https://www.kyero.com/en/property/19877577-country-house-for-sale-alaro | E235: 1 | G235: 126 | J235: Alaró | K235: 33.4 | L235: 33 | M235: 76.1 | N235: 66 | O235: 55.9 | P235: 49 | Q235: 73.8 | R235: 62 | S235: 2220000 | U235: 17619 | AH235: Quelle: Kyero
A236: 49 | B236: Villa in Port D'andratx, Mallorca | C236: https://www.kyero.com/en/property/15784908-villa-for-sale-port-d-andratx | E236: 4 | G236: 1039 | J236: Port D'andratx | K236: 43.5 | L236: 38 | M236: 86.2 | N236: 71 | O236: 6.3 | P236: 11 | Q236: 83.9 | R236: 68 | S236: 3950000 | U236: 3802 | AH236: Quelle: Kyero
A237: 50 | B237: Villa in Port de Valldemossa, Mallorca | C237: https://www.kyero.com/en/property/20502806-villa-for-sale-port-de-valldemossa | E237: 4 | G237: 840 | J237: Valldemossa | K237: 27.2 | L237: 32 | M237: 69.9 | N237: 64 | O237: 45.5 | P237: 44 | Q237: 67.6 | R237: 61 | S237: 2175000 | U237: 2589 | AH237: Quelle: Kyero
A238: 51 | B238: Country house in Es Capdella, Mallorca | C238: https://www.kyero.com/en/property/17707649-country-house-for-sale-es-capdella | E238: 5 | G238: 1910 | J238: Mallorca | K238: 47.4 | L238: 40 | M238: 51.8 | N238: 55 | O238: 70 | P238: 56 | Q238: 49.5 | R238: 51 | S238: 4500000 | U238: 2356 | AH238: Quelle: Kyero
A239: 52 | B239: Villa in Calvia, Mallorca | C239: https://www.kyero.com/en/property/20468251-villa-for-sale-calvia | E239: 5 | J239: Mallorca | K239: 47.4 | L239: 40 | M239: 51.8 | N239: 55 | O239: 70 | P239: 56 | Q239: 49.5 | R239: 51 | S239: 2500000 | AH239: Quelle: Kyero
A240: 53 | B240: Villa in Llucmajor, Mallorca | C240: https://www.kyero.com/en/property/18045290-villa-for-sale-llucmajor | E240: 4 | G240: 837 | J240: Llucmajor | K240: 22 | L240: 21 | M240: 28.2 | N240: 33 | O240: 60.2 | P240: 48 | Q240: 25.9 | R240: 29 | S240: 3000000 | U240: 3584 | AH240: Quelle: Kyero
A241: 54 | B241: Villa in Calvia, Mallorca | C241: https://www.kyero.com/en/property/17164637-villa-for-sale-calvia | E241: 4 | G241: 2941 | J241: Mallorca | K241: 47.4 | L241: 40 | M241: 51.8 | N241: 55 | O241: 70 | P241: 56 | Q241: 49.5 | R241: 51 | S241: 2250000 | U241: 765 | AH241: Quelle: Kyero
A242: 55 | B242: Villa in Sa Torre, Mallorca | C242: https://www.kyero.com/en/property/20338535-villa-for-sale-sa-torre | E242: 4 | G242: 986 | J242: Mallorca | K242: 47.4 | L242: 40 | M242: 51.8 | N242: 55 | O242: 70 | P242: 56 | Q242: 49.5 | R242: 51 | S242: 2995000 | U242: 3038 | AH242: Quelle: Kyero
A243: 56 | B243: Villa in Marratxinet (Marratxi), Mallorca | C243: https://www.kyero.com/en/property/18592573-villa-for-sale-marratxinet-marratxi | E243: 5 | G243: 22078 | J243: Mallorca | K243: 47.4 | L243: 40 | M243: 51.8 | N243: 55 | O243: 70 | P243: 56 | Q243: 49.5 | R243: 51 | S243: 3200000 | U243: 145 | AH243: Quelle: Kyero
A244: 57 | B244: Villa in Cala Vinyes, Mallorca | C244: https://www.kyero.com/en/property/11019109-villa-for-sale-cala-vinyes | E244: 5 | G244: 1287 | J244: Mallorca | K244: 47.4 | L244: 40 | M244: 51.8 | N244: 55 | O244: 70 | P244: 56 | Q244: 49.5 | R244: 51 | S244: 3300000 | U244: 2564 | AH244: Quelle: Kyero
A245: 58 | B245: Country house in Alaro, Mallorca | C245: https://www.kyero.com/en/property/19258591-country-house-for-sale-alaro | E245: 4 | G245: 16450 | J245: Mallorca | K245: 47.4 | L245: 40 | M245: 51.8 | N245: 55 | O245: 70 | P245: 56 | Q245: 49.5 | R245: 51 | S245: 3200000 | U245: 195 | AH245: Quelle: Kyero
A246: 59 | B246: Penthouse in Palma De Mallorca, Mallorca | C246: https://www.kyero.com/en/property/20533857-apartment-for-sale-palma-de-mallorca | E246: 3 | J246: Palma | K246: 9.7 | L246: 14 | M246: 52.5 | N246: 47 | O246: 32.1 | P246: 36 | Q246: 50.2 | R246: 44 | S246: 3450000 | AH246: Quelle: Kyero
A247: 60 | B247: Villa in Alaro, Mallorca | C247: https://www.kyero.com/en/property/19217447-villa-for-sale-alaro | E247: 17 | G247: 310 | J247: Alaró | K247: 33.4 | L247: 33 | M247: 76.1 | N247: 66 | O247: 55.9 | P247: 49 | Q247: 73.8 | R247: 62 | S247: 2200000 | U247: 7097 | AH247: Quelle: Kyero
A248: 61 | B248: Villa in Santa Ponsa, Mallorca | C248: https://www.kyero.com/en/property/20165770-villa-for-sale-santa-ponsa | E248: 5 | G248: 456 | J248: Santa Ponsa | K248: 31.1 | L248: 28 | M248: 73.9 | N248: 61 | O248: 15.2 | P248: 19 | Q248: 71.6 | R248: 57 | S248: 2500000 | U248: 5482 | AH248: Quelle: Kyero
A249: 62 | B249: Villa in Portals Nous, Mallorca | C249: https://www.kyero.com/en/property/17925956-villa-for-sale-portals-nous | E249: 5 | G249: 767 | J249: Portals Nous | K249: 23.8 | L249: 23 | M249: 66.6 | N249: 56 | O249: 21.8 | P249: 22 | Q249: 64.3 | R249: 52 | S249: 6500000 | U249: 8475 | AH249: Quelle: Kyero
A250: 63 | B250: Villa in Manacor, Mallorca | C250: https://www.kyero.com/en/property/19741147-villa-for-sale-manacor | E250: 5 | G250: 26258 | J250: Manacor | K250: 49.2 | L250: 44 | M250: 40.3 | N250: 45 | O250: 83.4 | P250: 68 | Q250: 38 | R250: 41 | S250: 3890000 | U250: 148 | AH250: Quelle: Kyero
A251: 64 | B251: Country house in Andratx, Mallorca | C251: https://www.kyero.com/en/property/19513769-country-house-for-sale-andratx | E251: 5 | G251: 163000 | J251: Andratx | K251: 40.3 | L251: 36 | M251: 83 | N251: 68 | O251: 2.7 | P251: 7 | Q251: 80.7 | R251: 65 | S251: 3950000 | U251: 24 | AH251: Quelle: Kyero
A252: 65 | B252: Country house in Manacor, Mallorca | C252: https://www.kyero.com/en/property/19651830-country-house-for-sale-manacor | E252: 4 | G252: 14700 | J252: Manacor | K252: 49.2 | L252: 44 | M252: 40.3 | N252: 45 | O252: 83.4 | P252: 68 | Q252: 38 | R252: 41 | S252: 2975000 | U252: 202 | AH252: Quelle: Kyero
A253: 66 | B253: Country house in Capdepera, Mallorca | C253: https://www.kyero.com/en/property/17958855-country-house-for-sale-capdepera | E253: 3 | G253: 16156 | J253: Mallorca | K253: 47.4 | L253: 40 | M253: 51.8 | N253: 55 | O253: 70 | P253: 56 | Q253: 49.5 | R253: 51 | S253: 4000000 | U253: 248 | AH253: Quelle: Kyero
A254: 67 | B254: Country house in Sant Llorenc Des Cardassar, Mallorca | C254: https://www.kyero.com/en/property/20509140-country-house-for-sale-sant-llorenc-des-cardassar | E254: 6 | G254: 121156 | J254: Manacor | K254: 49.2 | L254: 44 | M254: 40.3 | N254: 45 | O254: 83.4 | P254: 68 | Q254: 38 | R254: 41 | S254: 3950000 | U254: 33 | AH254: Quelle: Kyero
A255: 68 | B255: Country house in Arta, Mallorca | C255: https://www.kyero.com/en/property/11345873-country-house-for-sale-arta | E255: 4 | G255: 131000 | J255: Mallorca | K255: 47.4 | L255: 40 | M255: 51.8 | N255: 55 | O255: 70 | P255: 56 | Q255: 49.5 | R255: 51 | S255: 3750000 | U255: 29 | AH255: Quelle: Kyero
A256: 69 | B256: Barrio Sa Casa Blanca – chalet | C256: https://www.idealista.com/inmueble/110695172/ | E256: 6 | H256: 480 | J256: Palma | K256: 9.7 | L256: 14 | M256: 52.5 | N256: 47 | O256: 32.1 | P256: 36 | Q256: 50.2 | R256: 44 | S256: 2500000 | T256: 5208 | AH256: Quelle: Idealista
A257: 70 | B257: Barrio Son Espanyolet – chalet | C257: https://www.idealista.com/inmueble/110672299/ | E257: 7 | H257: 750 | J257: Palma | K257: 9.7 | L257: 14 | M257: 52.5 | N257: 47 | O257: 32.1 | P257: 36 | Q257: 50.2 | R257: 44 | S257: 5900000 | T257: 7867 | AH257: Quelle: Idealista
A258: 71 | B258: Barrio La Soledat – chalet | C258: https://www.idealista.com/inmueble/110672200/ | E258: 7 | H258: 790 | J258: Palma | K258: 9.7 | L258: 14 | M258: 52.5 | N258: 47 | O258: 32.1 | P258: 36 | Q258: 50.2 | R258: 44 | S258: 6200000 | T258: 7848 | AH258: Quelle: Idealista
A259: 72 | B259: calle Albercuix – chalet | C259: https://www.idealista.com/inmueble/110672146/ | E259: 6 | H259: 650 | J259: Palma | K259: 9.7 | L259: 14 | M259: 52.5 | N259: 47 | O259: 32.1 | P259: 36 | Q259: 50.2 | R259: 44 | S259: 5650000 | T259: 8692 | AH259: Quelle: Idealista
A260: 73 | B260: calle Albercuix – chalet | C260: https://www.idealista.com/inmueble/110672109/ | E260: 5 | H260: 620 | J260: Palma | K260: 9.7 | L260: 14 | M260: 52.5 | N260: 47 | O260: 32.1 | P260: 36 | Q260: 50.2 | R260: 44 | S260: 4950000 | T260: 7984 | AH260: Quelle: Idealista
A261: 74 | B261: Barrio Son Vida – chalet | C261: https://www.idealista.com/inmueble/110655777/ | E261: 5 | H261: 600 | J261: Palma | K261: 9.7 | L261: 14 | M261: 52.5 | N261: 47 | O261: 32.1 | P261: 36 | Q261: 50.2 | R261: 44 | S261: 6495000 | T261: 10825 | AH261: Quelle: Idealista
A262: 75 | B262: Barrio Son Dureta – chalet | C262: https://www.idealista.com/inmueble/110654888/ | E262: 6 | H262: 606 | J262: Palma | K262: 9.7 | L262: 14 | M262: 52.5 | N262: 47 | O262: 32.1 | P262: 36 | Q262: 50.2 | R262: 44 | S262: 2990000 | T262: 4934 | AH262: Quelle: Idealista
A263: 76 | B263: Barrio Son Gual – chalet | C263: https://www.idealista.com/inmueble/110645477/ | E263: 6 | H263: 396 | J263: Palma | K263: 9.7 | L263: 14 | M263: 52.5 | N263: 47 | O263: 32.1 | P263: 36 | Q263: 50.2 | R263: 44 | S263: 2640000 | T263: 6667 | AH263: Quelle: Idealista
A264: 77 | B264: calle del Rector Vives, 67 – chalet | C264: https://www.idealista.com/inmueble/110636189/ | E264: 5 | H264: 1118 | J264: Palma | K264: 9.7 | L264: 14 | M264: 52.5 | N264: 47 | O264: 32.1 | P264: 36 | Q264: 50.2 | R264: 44 | S264: 4150000 | T264: 3712 | AH264: Quelle: Idealista
A265: 78 | B265: Barrio Sindicat – chalet | C265: https://www.idealista.com/inmueble/102431198/ | E265: 5 | H265: 490 | J265: Palma | K265: 9.7 | L265: 14 | M265: 52.5 | N265: 47 | O265: 32.1 | P265: 36 | Q265: 50.2 | R265: 44 | S265: 4500000 | T265: 9184 | AH265: Quelle: Idealista
A266: 79 | B266: calle de Victorio Luzuriaga – chalet | C266: https://www.idealista.com/inmueble/104138534/ | E266: 5 | H266: 450 | J266: Palma | K266: 9.7 | L266: 14 | M266: 52.5 | N266: 47 | O266: 32.1 | P266: 36 | Q266: 50.2 | R266: 44 | S266: 3500000 | T266: 7778 | AH266: Quelle: Idealista
A267: 80 | B267: Barrio S'Aranjassa - Es Pil.larí – countryHouse | C267: https://www.idealista.com/inmueble/110468113/ | E267: 5 | H267: 300 | J267: Palma | K267: 9.7 | L267: 14 | M267: 52.5 | N267: 47 | O267: 32.1 | P267: 36 | Q267: 50.2 | R267: 44 | S267: 2700000 | T267: 9000 | AH267: Quelle: Idealista
... A2005: 1818 | B2005: Finca rústica | C2005: https://www.idealista.com/inmueble/106625101/ | E2005: 5 | H2005: 430 | J2005: Villafranca de Bonany | K2005: 37.1 | L2005: 33 | M2005: 35.2 | N2005: 38 | O2005: 71.3 | P2005: 57 | Q2005: 32.9 | R2005: 34 | S2005: 2250000 | T2005: 5233 | AH2005: Quelle: Idealista
A2006: 1819 | B2006: Property type | C2006: https://www.green-acres.es/en/blog/living-valencia | E2006: 3 | J2006: Mallorca | AH2006: Quelle: Green-Acres
A2007: 1820 | B2007: New building | C2007: https://english.habitaclia.com//english.habitaclia.com/new_building-province-mallorca.htm | J2007: Mallorca | AH2007: Quelle: Habitaclia
A2008: 1821 | B2008: Rent | C2008: https://english.habitaclia.com//english.habitaclia.com/rent-province-mallorca.htm | J2008: Mallorca | AH2008: Quelle: Habitaclia
A2009: 1822 | B2009: Transfer | C2009: https://english.habitaclia.com//english.habitaclia.com/transfer.htm | J2009: Mallorca | AH2009: Quelle: Habitaclia
A2010: 1823 | B2010: Homes | C2010: https://english.habitaclia.com//english.habitaclia.com/homes-province-mallorca.htm | J2010: Mallorca | AH2010: Quelle: Habitaclia
...

Sheet Einstellungen
A1: Bewertungssystem Einstellungen (blau = anpassbar)
A4: GEWICHTE (Summe = 100)
A5: Zimmer & Platz | B5: 20
A6: Erreichbarkeit (Flughafen/Daia/Andratx/Ses Salines) | B6: 10
A7: Grundstück & Garten | B7: 15
A8: Vermietlizenz | B8: 10
A9: Preis/Budget | B9: 15
A10: Charme / Ästhetik (1-5, manuell) | B10: 10
A11: Renovierung (0-100) | B11: 0
A12: Bewirtschaftung (1-5, 5=pflegeleicht) | B12: 5
A13: Preis-Leistung (€/m²) | B13: 15
A14: Summe | B14: =SUM(B5:B13)
A16: ERREICHBARKEIT (Minuten) | B16: Ideal | C16: Akzeptabel | D16: Dealbreaker | E16: Gewicht intern
A17: Flughafen | B17: 20 | C17: 35 | D17: 50 | E17: 25
A18: Daia (Hotel Corazón) | B18: 20 | C18: 40 | D18: 70 | E18: 40
A19: Andratx | B19: 30 | C19: 45 | D19: 60 | E19: 15
A20: Ses Salines | B20: 15 | C20: 30 | D20: 45 | E20: 20
A22: ZIMMER
A23: Minimum Zimmer | B23: 5
A24: Ideal Zimmer | B24: 8
A26: GRUNDSTÜCK & GARTEN
A27: Min Grundstück (m²) | B27: 3000
A28: Ideal Grundstück (m²) | B28: 15000
A29: Min Garten/Rasen (m²) | B29: 1000
A30: Ideal Garten/Rasen (m²) | B30: 5000
A32: VALUE
A33: Ziel €/m² (bebaut) | B33: 5000
A34: Max €/m² (bebaut) | B34: 12000

Sheet Rangliste
A1: Rangliste (automatisch aus 'Objekte')
A3: Rang | B3: Name | C3: Score | D3: Erreichb. | E3: Flugh.(min) | F3: Daia (min) | G3: Andratx (min) | H3: Zimmer | I3: Grundstück | J3: Garten | K3: Preis (€) | L3: Lizenz | M3: Charme | N3: Bewirtsch. | O3: Kommentar | P3: URL | Q3: Reno-Score | R3: Baujahr
A4: 1 | B4: =IFERROR(INDEX(Objekte!$B$2:$B$201,MATCH($A4,Objekte!$Z$2:$Z$201,0)),"") | C4: =IFERROR(INDEX(Objekte!$X$2:$X$201,MATCH($A4,Objekte!$Z$2:$Z$201,0)),"") | D4: =IFERROR(INDEX(Objekte!$W$2:$W$201,MATCH($A4,Objekte!$Z$2:$Z$201,0)),"") | E4: =IFERROR(INDEX(Objekte!$L$2:$L$201,MATCH($A4,Objekte!$Z$2:$Z$201,0)),"") | F4: =IFERROR(INDEX(Objekte!$N$2:$N$201,MATCH($A4,Objekte!$Z$2:$Z$201,0)),"") | G4: =IFERROR(INDEX(Objekte!$P$2:$P$201,MATCH($A4,Objekte!$Z$2:$Z$201,0)),"") | H4: =IFERROR(INDEX(Objekte!$E$2:$E$201,MATCH($A4,Objekte!$Z$2:$Z$201,0)),"") | I4: =IFERROR(INDEX(Objekte!$G$2:$G$201,MATCH($A4,Objekte!$Z$2:$Z$201,0)),"") | J4: =IFERROR(INDEX(Objekte!$I$2:$I$201,MATCH($A4,Objekte!$Z$2:$Z$201,0)),"") | K4: =IFERROR(INDEX(Objekte!$Q$2:$Q$201,MATCH($A4,Objekte!$Z$2:$Z$201,0)),"") | L4: =IFERROR(INDEX(Objekte!$V$2:$V$201,MATCH($A4,Objekte!$Z$2:$Z$201,0)),"") | M4: =IFERROR(INDEX(Objekte!$D$2:$D$201,MATCH($A4,Objekte!$Z$2:$Z$201,0)),"") | N4: =IFERROR(INDEX(Objekte!$U$2:$U$201,MATCH($A4,Objekte!$Z$2:$Z$201,0)),"") | O4: =IFERROR(INDEX(Objekte!$AF$2:$AF$201,MATCH($A4,Objekte!$Z$2:$Z$201,0)),"") | P4: =IFERROR(INDEX(Objekte!$C$2:$C$201,MATCH($A4,Objekte!$Z$2:$Z$201,0)),"") | Q4: =IFERROR(INDEX(Objekte!$AD$2:$AD$201,MATCH($A4,Objekte!$Z$2:$Z$201,0)),"") | R4: =IFERROR(INDEX(Objekte!$AB$2:$AB$201,MATCH($A4,Objekte!$Z$2:$Z$201,0)),"")
A5: 2 | B5: =IFERROR(INDEX(Objekte!$B$2:$B$201,MATCH($A5,Objekte!$Z$2:$Z$201,0)),"") | C5: =IFERROR(INDEX(Objekte!$X$2:$X$201,MATCH($A5,Objekte!$Z$2:$Z$201,0)),"") | D5: =IFERROR(INDEX(Objekte!$W$2:$W$201,MATCH($A5,Objekte!$Z$2:$Z$201,0)),"") | E5: =IFERROR(INDEX(Objekte!$L$2:$L$201,MATCH($A5,Objekte!$Z$2:$Z$201,0)),"") | F5: =IFERROR(INDEX(Objekte!$N$2:$N$201,MATCH($A5,Objekte!$Z$2:$Z$201,0)),"") | G5: =IFERROR(INDEX(Objekte!$P$2:$P$201,MATCH($A5,Objekte!$Z$2:$Z$201,0)),"") | H5: =IFERROR(INDEX(Objekte!$E$2:$E$201,MATCH($A5,Objekte!$Z$2:$Z$201,0)),"") | I5: =IFERROR(INDEX(Objekte!$G$2:$G$201,MATCH($A5,Objekte!$Z$2:$Z$201,0)),"") | J5: =IFERROR(INDEX(Objekte!$I$2:$I$201,MATCH($A5,Objekte!$Z$2:$Z$201,0)),"") | K5: =IFERROR(INDEX(Objekte!$Q$2:$Q$201,MATCH($A5,Objekte!$Z$2:$Z$201,0)),"") | L5: =IFERROR(INDEX(Objekte!$V$2:$V$201,MATCH($A5,Objekte!$Z$2:$Z$201,0)),"") | M5: =IFERROR(INDEX(Objekte!$D$2:$D$201,MATCH($A5,Objekte!$Z$2:$Z$201,0)),"") | N5: =IFERROR(INDEX(Objekte!$U$2:$U$201,MATCH($A5,Objekte!$Z$2:$Z$201,0)),"") | O5: =IFERROR(INDEX(Objekte!$AF$2:$AF$201,MATCH($A5,Objekte!$Z$2:$Z$201,0)),"") | P5: =IFERROR(INDEX(Objekte!$C$2:$C$201,MATCH($A5,Objekte!$Z$2:$Z$201,0)),"") | Q5: =IFERROR(INDEX(Objekte!$AD$2:$AD$201,MATCH($A5,Objekte!$Z$2:$Z$201,0)),"") | R5: =IFERROR(INDEX(Objekte!$AB$2:$AB$201,MATCH($A5,Objekte!$Z$2:$Z$201,0)),"")
A6: 3 | B6: =IFERROR(INDEX(Objekte!$B$2:$B$201,MATCH($A6,Objekte!$Z$2:$Z$201,0)),"") | C6: =IFERROR(INDEX(Objekte!$X$2:$X$201,MATCH($A6,Objekte!$Z$2:$Z$201,0)),"") | D6: =IFERROR(INDEX(Objekte!$W$2:$W$201,MATCH($A6,Objekte!$Z$2:$Z$201,0)),"") | E6: =IFERROR(INDEX(Objekte!$L$2:$L$201,MATCH($A6,Objekte!$Z$2:$Z$201,0)),"") | F6: =IFERROR(INDEX(Objekte!$N$2:$N$201,MATCH($A6,Objekte!$Z$2:$Z$201,0)),"") | G6: =IFERROR(INDEX(Objekte!$P$2:$P$201,MATCH($A6,Objekte!$Z$2:$Z$201,0)),"") | H6: =IFERROR(INDEX(Objekte!$E$2:$E$201,MATCH($A6,Objekte!$Z$2:$Z$201,0)),"") | I6: =IFERROR(INDEX(Objekte!$G$2:$G$201,MATCH($A6,Objekte!$Z$2:$Z$201,0)),"") | J6: =IFERROR(INDEX(Objekte!$I$2:$I$201,MATCH($A6,Objekte!$Z$2:$Z$201,0)),"") | K6: =IFERROR(INDEX(Objekte!$Q$2:$Q$201,MATCH($A6,Objekte!$Z$2:$Z$201,0)),"") | L6: =IFERROR(INDEX(Objekte!$V$2:$V$201,MATCH($A6,Objekte!$Z$2:$Z$201,0)),"") | M6: =IFERROR(INDEX(Objekte!$D$2:$D$201,MATCH($A6,Objekte!$Z$2:$Z$201,0)),"") | N6: =IFERROR(INDEX(Objekte!$U$2:$U$201,MATCH($A6,Objekte!$Z$2:$Z$201,0)),"") | O6: =IFERROR(INDEX(Objekte!$AF$2:$AF$201,MATCH($A6,Objekte!$Z$2:$Z$201,0)),"") | P6: =IFERROR(INDEX(Objekte!$C$2:$C$201,MATCH($A6,Objekte!$Z$2:$Z$201,0)),"") | Q6: =IFERROR(INDEX(Objekte!$AD$2:$AD$201,MATCH($A6,Objekte!$Z$2:$Z$201,0)),"") | R6: =IFERROR(INDEX(Objekte!$AB$2:$AB$201,MATCH($A6,Objekte!$Z$2:$Z$201,0)),"")
A7: 4 | B7: =IFERROR(INDEX(Objekte!$B$2:$B$201,MATCH($A7,Objekte!$Z$2:$Z$201,0)),"") | C7: =IFERROR(INDEX(Objekte!$X$2:$X$201,MATCH($A7,Objekte!$Z$2:$Z$201,0)),"") | D7: =IFERROR(INDEX(Objekte!$W$2:$W$201,MATCH($A7,Objekte!$Z$2:$Z$201,0)),"") | E7: =IFERROR(INDEX(Objekte!$L$2:$L$201,MATCH($A7,Objekte!$Z$2:$Z$201,0)),"") | F7: =IFERROR(INDEX(Objekte!$N$2:$N$201,MATCH($A7,Objekte!$Z$2:$Z$201,0)),"") | G7: =IFERROR(INDEX(Objekte!$P$2:$P$201,MATCH($A7,Objekte!$Z$2:$Z$201,0)),"") | H7: =IFERROR(INDEX(Objekte!$E$2:$E$201,MATCH($A7,Objekte!$Z$2:$Z$201,0)),"") | I7: =IFERROR(INDEX(Objekte!$G$2:$G$201,MATCH($A7,Objekte!$Z$2:$Z$201,0)),"") | J7: =IFERROR(INDEX(Objekte!$I$2:$I$201,MATCH($A7,Objekte!$Z$2:$Z$201,0)),"") | K7: =IFERROR(INDEX(Objekte!$Q$2:$Q$201,MATCH($A7,Objekte!$Z$2:$Z$201,0)),"") | L7: =IFERROR(INDEX(Objekte!$V$2:$V$201,MATCH($A7,Objekte!$Z$2:$Z$201,0)),"") | M7: =IFERROR(INDEX(Objekte!$D$2:$D$201,MATCH($A7,Objekte!$Z$2:$Z$201,0)),"") | N7: =IFERROR(INDEX(Objekte!$U$2:$U$201,MATCH($A7,Objekte!$Z$2:$Z$201,0)),"") | O7: =IFERROR(INDEX(Objekte!$AF$2:$AF$201,MATCH($A7,Objekte!$Z$2:$Z$201,0)),"") | P7: =IFERROR(INDEX(Objekte!$C$2:$C$201,MATCH($A7,Objekte!$Z$2:$Z$201,0)),"") | Q7: =IFERROR(INDEX(Objekte!$AD$2:$AD$201,MATCH($A7,Objekte!$Z$2:$Z$201,0)),"") | R7: =IFERROR(INDEX(Objekte!$AB$2:$AB$201,MATCH($A7,Objekte!$Z$2:$Z$201,0)),"")
A8: 5 | B8: =IFERROR(INDEX(Objekte!$B$2:$B$201,MATCH($A8,Objekte!$Z$2:$Z$201,0)),"") | C8: =IFERROR(INDEX(Objekte!$X$2:$X$201,MATCH($A8,Objekte!$Z$2:$Z$201,0)),"") | D8: =IFERROR(INDEX(Objekte!$W$2:$W$201,MATCH($A8,Objekte!$Z$2:$Z$201,0)),"") | E8: =IFERROR(INDEX(Objekte!$L$2:$L$201,MATCH($A8,Objekte!$Z$2:$Z$201,0)),"") | F8: =IFERROR(INDEX(Objekte!$N$2:$N$201,MATCH($A8,Objekte!$Z$2:$Z$201,0)),"") | G8: =IFERROR(INDEX(Objekte!$P$2:$P$201,MATCH($A8,Objekte!$Z$2:$Z$201,0)),"") | H8: =IFERROR(INDEX(Objekte!$E$2:$E$201,MATCH($A8,Objekte!$Z$2:$Z$201,0)),"") | I8: =IFERROR(INDEX(Objekte!$G$2:$G$201,MATCH($A8,Objekte!$Z$2:$Z$201,0)),"") | J8: =IFERROR(INDEX(Objekte!$I$2:$I$201,MATCH($A8,Objekte!$Z$2:$Z$201,0)),"") | K8: =IFERROR(INDEX(Objekte!$Q$2:$Q$201,MATCH($A8,Objekte!$Z$2:$Z$201,0)),"") | L8: =IFERROR(INDEX(Objekte!$V$2:$V$201,MATCH($A8,Objekte!$Z$2:$Z$201,0)),"") | M8: =IFERROR(INDEX(Objekte!$D$2:$D$201,MATCH($A8,Objekte!$Z$2:$Z$201,0)),"") | N8: =IFERROR(INDEX(Objekte!$U$2:$U$201,MATCH($A8,Objekte!$Z$2:$Z$201,0)),"") | O8: =IFERROR(INDEX(Objekte!$AF$2:$AF$201,MATCH($A8,Objekte!$Z$2:$Z$201,0)),"") | P8: =IFERROR(INDEX(Objekte!$C$2:$C$201,MATCH($A8,Objekte!$Z$2:$Z$201,0)),"") | Q8: =IFERROR(INDEX(Objekte!$AD$2:$AD$201,MATCH($A8,Objekte!$Z$2:$Z$201,0)),"") | R8: =IFERROR(INDEX(Objekte!$AB$2:$AB$201,MATCH($A8,Objekte!$Z$2:$Z$201,0)),"")
A9: 6 | B9: =IFERROR(INDEX(Objekte!$B$2:$B$201,MATCH($A9,Objekte!$Z$2:$Z$201,0)),"") | C9: =IFERROR(INDEX(Objekte!$X$2:$X$201,MATCH($A9,Objekte!$Z$2:$Z$201,0)),"") | D9: =IFERROR(INDEX(Objekte!$W$2:$W$201,MATCH($A9,Objekte!$Z$2:$Z$201,0)),"") | E9: =IFERROR(INDEX(Objekte!$L$2:$L$201,MATCH($A9,Objekte!$Z$2:$Z$201,0)),"") | F9: =IFERROR(INDEX(Objekte!$N$2:$N$201,MATCH($A9,Objekte!$Z$2:$Z$201,0)),"") | G9: =IFERROR(INDEX(Objekte!$P$2:$P$201,MATCH($A9,Objekte!$Z$2:$Z$201,0)),"") | H9: =IFERROR(INDEX(Objekte!$E$2:$E$201,MATCH($A9,Objekte!$Z$2:$Z$201,0)),"") | I9: =IFERROR(INDEX(Objekte!$G$2:$G$201,MATCH($A9,Objekte!$Z$2:$Z$201,0)),"") | J9: =IFERROR(INDEX(Objekte!$I$2:$I$201,MATCH($A9,Objekte!$Z$2:$Z$201,0)),"") | K9: =IFERROR(INDEX(Objekte!$Q$2:$Q$201,MATCH($A9,Objekte!$Z$2:$Z$201,0)),"") | L9: =IFERROR(INDEX(Objekte!$V$2:$V$201,MATCH($A9,Objekte!$Z$2:$Z$201,0)),"") | M9: =IFERROR(INDEX(Objekte!$D$2:$D$201,MATCH($A9,Objekte!$Z$2:$Z$201,0)),"") | N9: =IFERROR(INDEX(Objekte!$U$2:$U$201,MATCH($A9,Objekte!$Z$2:$Z$201,0)),"") | O9: =IFERROR(INDEX(Objekte!$AF$2:$AF$201,MATCH($A9,Objekte!$Z$2:$Z$201,0)),"") | P9: =IFERROR(INDEX(Objekte!$C$2:$C$201,MATCH($A9,Objekte!$Z$2:$Z$201,0)),"") | Q9: =IFERROR(INDEX(Objekte!$AD$2:$AD$201,MATCH($A9,Objekte!$Z$2:$Z$201,0)),"") | R9: =IFERROR(INDEX(Objekte!$AB$2:$AB$201,MATCH($A9,Objekte!$Z$2:$Z$201,0)),"")
A10: 7 | B10: =IFERROR(INDEX(Objekte!$B$2:$B$201,MATCH($A10,Objekte!$Z$2:$Z$201,0)),"") | C10: =IFERROR(INDEX(Objekte!$X$2:$X$201,MATCH($A10,Objekte!$Z$2:$Z$201,0)),"") | D10: =IFERROR(INDEX(Objekte!$W$2:$W$201,MATCH($A10,Objekte!$Z$2:$Z$201,0)),"") | E10: =IFERROR(INDEX(Objekte!$L$2:$L$201,MATCH($A10,Objekte!$Z$2:$Z$201,0)),"") | F10: =IFERROR(INDEX(Objekte!$N$2:$N$201,MATCH($A10,Objekte!$Z$2:$Z$201,0)),"") | G10: =IFERROR(INDEX(Objekte!$P$2:$P$201,MATCH($A10,Objekte!$Z$2:$Z$201,0)),"") | H10: =IFERROR(INDEX(Objekte!$E$2:$E$201,MATCH($A10,Objekte!$Z$2:$Z$201,0)),"") | I10: =IFERROR(INDEX(Objekte!$G$2:$G$201,MATCH($A10,Objekte!$Z$2:$Z$201,0)),"") | J10: =IFERROR(INDEX(Objekte!$I$2:$I$201,MATCH($A10,Objekte!$Z$2:$Z$201,0)),"") | K10: =IFERROR(INDEX(Objekte!$Q$2:$Q$201,MATCH($A10,Objekte!$Z$2:$Z$201,0)),"") | L10: =IFERROR(INDEX(Objekte!$V$2:$V$201,MATCH($A10,Objekte!$Z$2:$Z$201,0)),"") | M10: =IFERROR(INDEX(Objekte!$D$2:$D$201,MATCH($A10,Objekte!$Z$2:$Z$201,0)),"") | N10: =IFERROR(INDEX(Objekte!$U$2:$U$201,MATCH($A10,Objekte!$Z$2:$Z$201,0)),"") | O10: =IFERROR(INDEX(Objekte!$AF$2:$AF$201,MATCH($A10,Objekte!$Z$2:$Z$201,0)),"") | P10: =IFERROR(INDEX(Objekte!$C$2:$C$201,MATCH($A10,Objekte!$Z$2:$Z$201,0)),"") | Q10: =IFERROR(INDEX(Objekte!$AD$2:$AD$201,MATCH($A10,Objekte!$Z$2:$Z$201,0)),"") | R10: =IFERROR(INDEX(Objekte!$AB$2:$AB$201,MATCH($A10,Objekte!$Z$2:$Z$201,0)),"")
A11: 8 | B11: =IFERROR(INDEX(Objekte!$B$2:$B$201,MATCH($A11,Objekte!$Z$2:$Z$201,0)),"") | C11: =IFERROR(INDEX(Objekte!$X$2:$X$201,MATCH($A11,Objekte!$Z$2:$Z$201,0)),"") | D11: =IFERROR(INDEX(Objekte!$W$2:$W$201,MATCH($A11,Objekte!$Z$2:$Z$201,0)),"") | E11: =IFERROR(INDEX(Objekte!$L$2:$L$201,MATCH($A11,Objekte!$Z$2:$Z$201,0)),"") | F11: =IFERROR(INDEX(Objekte!$N$2:$N$201,MATCH($A11,Objekte!$Z$2:$Z$201,0)),"") | G11: =IFERROR(INDEX(Objekte!$P$2:$P$201,MATCH($A11,Objekte!$Z$2:$Z$201,0)),"") | H11: =IFERROR(INDEX(Objekte!$E$2:$E$201,MATCH($A11,Objekte!$Z$2:$Z$201,0)),"") | I11: =IFERROR(INDEX(Objekte!$G$2:$G$201,MATCH($A11,Objekte!$Z$2:$Z$201,0)),"") | J11: =IFERROR(INDEX(Objekte!$I$2:$I$201,MATCH($A11,Objekte!$Z$2:$Z$201,0)),"") | K11: =IFERROR(INDEX(Objekte!$Q$2:$Q$201,MATCH($A11,Objekte!$Z$2:$Z$201,0)),"") | L11: =IFERROR(INDEX(Objekte!$V$2:$V$201,MATCH($A11,Objekte!$Z$2:$Z$201,0)),"") | M11: =IFERROR(INDEX(Objekte!$D$2:$D$201,MATCH($A11,Objekte!$Z$2:$Z$201,0)),"") | N11: =IFERROR(INDEX(Objekte!$U$2:$U$201,MATCH($A11,Objekte!$Z$2:$Z$201,0)),"") | O11: =IFERROR(INDEX(Objekte!$AF$2:$AF$201,MATCH($A11,Objekte!$Z$2:$Z$201,0)),"") | P11: =IFERROR(INDEX(Objekte!$C$2:$C$201,MATCH($A11,Objekte!$Z$2:$Z$201,0)),"") | Q11: =IFERROR(INDEX(Objekte!$AD$2:$AD$201,MATCH($A11,Objekte!$Z$2:$Z$201,0)),"") | R11: =IFERROR(INDEX(Objekte!$AB$2:$AB$201,MATCH($A11,Objekte!$Z$2:$Z$201,0)),"")
A12: 9 | B12: =IFERROR(INDEX(Objekte!$B$2:$B$201,MATCH($A12,Objekte!$Z$2:$Z$201,0)),"") | C12: =IFERROR(INDEX(Objekte!$X$2:$X$201,MATCH($A12,Objekte!$Z$2:$Z$201,0)),"") | D12: =IFERROR(INDEX(Objekte!$W$2:$W$201,MATCH($A12,Objekte!$Z$2:$Z$201,0)),"") | E12: =IFERROR(INDEX(Objekte!$L$2:$L$201,MATCH($A12,Objekte!$Z$2:$Z$201,0)),"") | F12: =IFERROR(INDEX(Objekte!$N$2:$N$201,MATCH($A12,Objekte!$Z$2:$Z$201,0)),"") | G12: =IFERROR(INDEX(Objekte!$P$2:$P$201,MATCH($A12,Objekte!$Z$2:$Z$201,0)),"") | H12: =IFERROR(INDEX(Objekte!$E$2:$E$201,MATCH($A12,Objekte!$Z$2:$Z$201,0)),"") | I12: =IFERROR(INDEX(Objekte!$G$2:$G$201,MATCH($A12,Objekte!$Z$2:$Z$201,0)),"") | J12: =IFERROR(INDEX(Objekte!$I$2:$I$201,MATCH($A12,Objekte!$Z$2:$Z$201,0)),"") | K12: =IFERROR(INDEX(Objekte!$Q$2:$Q$201,MATCH($A12,Objekte!$Z$2:$Z$201,0)),"") | L12: =IFERROR(INDEX(Objekte!$V$2:$V$201,MATCH($A12,Objekte!$Z$2:$Z$201,0)),"") | M12: =IFERROR(INDEX(Objekte!$D$2:$D$201,MATCH($A12,Objekte!$Z$2:$Z$201,0)),"") | N12: =IFERROR(INDEX(Objekte!$U$2:$U$201,MATCH($A12,Objekte!$Z$2:$Z$201,0)),"") | O12: =IFERROR(INDEX(Objekte!$AF$2:$AF$201,MATCH($A12,Objekte!$Z$2:$Z$201,0)),"") | P12: =IFERROR(INDEX(Objekte!$C$2:$C$201,MATCH($A12,Objekte!$Z$2:$Z$201,0)),"") | Q12: =IFERROR(INDEX(Objekte!$AD$2:$AD$201,MATCH($A12,Objekte!$Z$2:$Z$201,0)),"") | R12: =IFERROR(INDEX(Objekte!$AB$2:$AB$201,MATCH($A12,Objekte!$Z$2:$Z$201,0)),"")
A13: 10 | B13: =IFERROR(INDEX(Objekte!$B$2:$B$201,MATCH($A13,Objekte!$Z$2:$Z$201,0)),"") | C13: =IFERROR(INDEX(Objekte!$X$2:$X$201,MATCH($A13,Objekte!$Z$2:$Z$201,0)),"") | D13: =IFERROR(INDEX(Objekte!$W$2:$W$201,MATCH($A13,Objekte!$Z$2:$Z$201,0)),"") | E13: =IFERROR(INDEX(Objekte!$L$2:$L$201,MATCH($A13,Objekte!$Z$2:$Z$201,0)),"") | F13: =IFERROR(INDEX(Objekte!$N$2:$N$201,MATCH($A13,Objekte!$Z$2:$Z$201,0)),"") | G13: =IFERROR(INDEX(Objekte!$P$2:$P$201,MATCH($A13,Objekte!$Z$2:$Z$201,0)),"") | H13: =IFERROR(INDEX(Objekte!$E$2:$E$201,MATCH($A13,Objekte!$Z$2:$Z$201,0)),"") | I13: =IFERROR(INDEX(Objekte!$G$2:$G$201,MATCH($A13,Objekte!$Z$2:$Z$201,0)),"") | J13: =IFERROR(INDEX(Objekte!$I$2:$I$201,MATCH($A13,Objekte!$Z$2:$Z$201,0)),"") | K13: =IFERROR(INDEX(Objekte!$Q$2:$Q$201,MATCH($A13,Objekte!$Z$2:$Z$201,0)),"") | L13: =IFERROR(INDEX(Objekte!$V$2:$V$201,MATCH($A13,Objekte!$Z$2:$Z$201,0)),"") | M13: =IFERROR(INDEX(Objekte!$D$2:$D$201,MATCH($A13,Objekte!$Z$2:$Z$201,0)),"") | N13: =IFERROR(INDEX(Objekte!$U$2:$U$201,MATCH($A13,Objekte!$Z$2:$Z$201,0)),"") | O13: =IFERROR(INDEX(Objekte!$AF$2:$AF$201,MATCH($A13,Objekte!$Z$2:$Z$201,0)),"") | P13: =IFERROR(INDEX(Objekte!$C$2:$C$201,MATCH($A13,Objekte!$Z$2:$Z$201,0)),"") | Q13: =IFERROR(INDEX(Objekte!$AD$2:$AD$201,MATCH($A13,Objekte!$Z$2:$Z$201,0)),"") | R13: =IFERROR(INDEX(Objekte!$AB$2:$AB$201,MATCH($A13,Objekte!$Z$2:$Z$201,0)),"")
A14: 11 | B14: =IFERROR(INDEX(Objekte!$B$2:$B$201,MATCH($A14,Objekte!$Z$2:$Z$201,0)),"") | C14: =IFERROR(INDEX(Objekte!$X$2:$X$201,MATCH($A14,Objekte!$Z$2:$Z$201,0)),"") | D14: =IFERROR(INDEX(Objekte!$W$2:$W$201,MATCH($A14,Objekte!$Z$2:$Z$201,0)),"") | E14: =IFERROR(INDEX(Objekte!$L$2:$L$201,MATCH($A14,Objekte!$Z$2:$Z$201,0)),"") | F14: =IFERROR(INDEX(Objekte!$N$2:$N$201,MATCH($A14,Objekte!$Z$2:$Z$201,0)),"") | G14: =IFERROR(INDEX(Objekte!$P$2:$P$201,MATCH($A14,Objekte!$Z$2:$Z$201,0)),"") | H14: =IFERROR(INDEX(Objekte!$E$2:$E$201,MATCH($A14,Objekte!$Z$2:$Z$201,0)),"") | I14: =IFERROR(INDEX(Objekte!$G$2:$G$201,MATCH($A14,Objekte!$Z$2:$Z$201,0)),"") | J14: =IFERROR(INDEX(Objekte!$I$2:$I$201,MATCH($A14,Objekte!$Z$2:$Z$201,0)),"") | K14: =IFERROR(INDEX(Objekte!$Q$2:$Q$201,MATCH($A14,Objekte!$Z$2:$Z$201,0)),"") | L14: =IFERROR(INDEX(Objekte!$V$2:$V$201,MATCH($A14,Objekte!$Z$2:$Z$201,0)),"") | M14: =IFERROR(INDEX(Objekte!$D$2:$D$201,MATCH($A14,Objekte!$Z$2:$Z$201,0)),"") | N14: =IFERROR(INDEX(Objekte!$U$2:$U$201,MATCH($A14,Objekte!$Z$2:$Z$201,0)),"") | O14: =IFERROR(INDEX(Objekte!$AF$2:$AF$201,MATCH($A14,Objekte!$Z$2:$Z$201,0)),"") | P14: =IFERROR(INDEX(Objekte!$C$2:$C$201,MATCH($A14,Objekte!$Z$2:$Z$201,0)),"") | Q14: =IFERROR(INDEX(Objekte!$AD$2:$AD$201,MATCH($A14,Objekte!$Z$2:$Z$201,0)),"") | R14: =IFERROR(INDEX(Objekte!$AB$2:$AB$201,MATCH($A14,Objekte!$Z$2:$Z$201,0)),"")
A15: 12 | B15: =IFERROR(INDEX(Objekte!$B$2:$B$201,MATCH($A15,Objekte!$Z$2:$Z$201,0)),"") | C15: =IFERROR(INDEX(Objekte!$X$2:$X$201,MATCH($A15,Objekte!$Z$2:$Z$201,0)),"") | D15: =IFERROR(INDEX(Objekte!$W$2:$W$201,MATCH($A15,Objekte!$Z$2:$Z$201,0)),"") | E15: =IFERROR(INDEX(Objekte!$L$2:$L$201,MATCH($A15,Objekte!$Z$2:$Z$201,0)),"") | F15: =IFERROR(INDEX(Objekte!$N$2:$N$201,MATCH($A15,Objekte!$Z$2:$Z$201,0)),"") | G15: =IFERROR(INDEX(Objekte!$P$2:$P$201,MATCH($A15,Objekte!$Z$2:$Z$201,0)),"") | H15: =IFERROR(INDEX(Objekte!$E$2:$E$201,MATCH($A15,Objekte!$Z$2:$Z$201,0)),"") | I15: =IFERROR(INDEX(Objekte!$G$2:$G$201,MATCH($A15,Objekte!$Z$2:$Z$201,0)),"") | J15: =IFERROR(INDEX(Objekte!$I$2:$I$201,MATCH($A15,Objekte!$Z$2:$Z$201,0)),"") | K15: =IFERROR(INDEX(Objekte!$Q$2:$Q$201,MATCH($A15,Objekte!$Z$2:$Z$201,0)),"") | L15: =IFERROR(INDEX(Objekte!$V$2:$V$201,MATCH($A15,Objekte!$Z$2:$Z$201,0)),"") | M15: =IFERROR(INDEX(Objekte!$D$2:$D$201,MATCH($A15,Objekte!$Z$2:$Z$201,0)),"") | N15: =IFERROR(INDEX(Objekte!$U$2:$U$201,MATCH($A15,Objekte!$Z$2:$Z$201,0)),"") | O15: =IFERROR(INDEX(Objekte!$AF$2:$AF$201,MATCH($A15,Objekte!$Z$2:$Z$201,0)),"") | P15: =IFERROR(INDEX(Objekte!$C$2:$C$201,MATCH($A15,Objekte!$Z$2:$Z$201,0)),"") | Q15: =IFERROR(INDEX(Objekte!$AD$2:$AD$201,MATCH($A15,Objekte!$Z$2:$Z$201,0)),"") | R15: =IFERROR(INDEX(Objekte!$AB$2:$AB$201,MATCH($A15,Objekte!$Z$2:$Z$201,0)),"")
... A50: 47 | B50: =IFERROR(INDEX(Objekte!$B$2:$B$201,MATCH($A50,Objekte!$Z$2:$Z$201,0)),"") | C50: =IFERROR(INDEX(Objekte!$X$2:$X$201,MATCH($A50,Objekte!$Z$2:$Z$201,0)),"") | D50: =IFERROR(INDEX(Objekte!$W$2:$W$201,MATCH($A50,Objekte!$Z$2:$Z$201,0)),"") | E50: =IFERROR(INDEX(Objekte!$L$2:$L$201,MATCH($A50,Objekte!$Z$2:$Z$201,0)),"") | F50: =IFERROR(INDEX(Objekte!$N$2:$N$201,MATCH($A50,Objekte!$Z$2:$Z$201,0)),"") | G50: =IFERROR(INDEX(Objekte!$P$2:$P$201,MATCH($A50,Objekte!$Z$2:$Z$201,0)),"") | H50: =IFERROR(INDEX(Objekte!$E$2:$E$201,MATCH($A50,Objekte!$Z$2:$Z$201,0)),"") | I50: =IFERROR(INDEX(Objekte!$G$2:$G$201,MATCH($A50,Objekte!$Z$2:$Z$201,0)),"") | J50: =IFERROR(INDEX(Objekte!$I$2:$I$201,MATCH($A50,Objekte!$Z$2:$Z$201,0)),"") | K50: =IFERROR(INDEX(Objekte!$Q$2:$Q$201,MATCH($A50,Objekte!$Z$2:$Z$201,0)),"") | L50: =IFERROR(INDEX(Objekte!$V$2:$V$201,MATCH($A50,Objekte!$Z$2:$Z$201,0)),"") | M50: =IFERROR(INDEX(Objekte!$D$2:$D$201,MATCH($A50,Objekte!$Z$2:$Z$201,0)),"") | N50: =IFERROR(INDEX(Objekte!$U$2:$U$201,MATCH($A50,Objekte!$Z$2:$Z$201,0)),"") | O50: =IFERROR(INDEX(Objekte!$AF$2:$AF$201,MATCH($A50,Objekte!$Z$2:$Z$201,0)),"") | P50: =IFERROR(INDEX(Objekte!$C$2:$C$201,MATCH($A50,Objekte!$Z$2:$Z$201,0)),"") | Q50: =IFERROR(INDEX(Objekte!$AD$2:$AD$201,MATCH($A50,Objekte!$Z$2:$Z$201,0)),"") | R50: =IFERROR(INDEX(Objekte!$AB$2:$AB$201,MATCH($A50,Objekte!$Z$2:$Z$201,0)),"")
B51: =IFERROR(INDEX(Objekte!$B$2:$B$201,MATCH($A51,Objekte!$Z$2:$Z$201,0)),"") | C51: =IFERROR(INDEX(Objekte!$X$2:$X$201,MATCH($A51,Objekte!$Z$2:$Z$201,0)),"") | D51: =IFERROR(INDEX(Objekte!$W$2:$W$201,MATCH($A51,Objekte!$Z$2:$Z$201,0)),"") | E51: =IFERROR(INDEX(Objekte!$L$2:$L$201,MATCH($A51,Objekte!$Z$2:$Z$201,0)),"") | F51: =IFERROR(INDEX(Objekte!$N$2:$N$201,MATCH($A51,Objekte!$Z$2:$Z$201,0)),"") | G51: =IFERROR(INDEX(Objekte!$P$2:$P$201,MATCH($A51,Objekte!$Z$2:$Z$201,0)),"") | H51: =IFERROR(INDEX(Objekte!$E$2:$E$201,MATCH($A51,Objekte!$Z$2:$Z$201,0)),"") | I51: =IFERROR(INDEX(Objekte!$G$2:$G$201,MATCH($A51,Objekte!$Z$2:$Z$201,0)),"") | J51: =IFERROR(INDEX(Objekte!$I$2:$I$201,MATCH($A51,Objekte!$Z$2:$Z$201,0)),"") | K51: =IFERROR(INDEX(Objekte!$Q$2:$Q$201,MATCH($A51,Objekte!$Z$2:$Z$201,0)),"") | L51: =IFERROR(INDEX(Objekte!$V$2:$V$201,MATCH($A51,Objekte!$Z$2:$Z$201,0)),"") | M51: =IFERROR(INDEX(Objekte!$D$2:$D$201,MATCH($A51,Objekte!$Z$2:$Z$201,0)),"") | N51: =IFERROR(INDEX(Objekte!$U$2:$U$201,MATCH($A51,Objekte!$Z$2:$Z$201,0)),"") | O51: =IFERROR(INDEX(Objekte!$AF$2:$AF$201,MATCH($A51,Objekte!$Z$2:$Z$201,0)),"") | P51: =IFERROR(INDEX(Objekte!$C$2:$C$201,MATCH($A51,Objekte!$Z$2:$Z$201,0)),"") | Q51: =IFERROR(INDEX(Objekte!$AD$2:$AD$201,MATCH($A51,Objekte!$Z$2:$Z$201,0)),"") | R51: =IFERROR(INDEX(Objekte!$AB$2:$AB$201,MATCH($A51,Objekte!$Z$2:$Z$201,0)),"")
B52: =IFERROR(INDEX(Objekte!$B$2:$B$201,MATCH($A52,Objekte!$Z$2:$Z$201,0)),"") | C52: =IFERROR(INDEX(Objekte!$X$2:$X$201,MATCH($A52,Objekte!$Z$2:$Z$201,0)),"") | D52: =IFERROR(INDEX(Objekte!$W$2:$W$201,MATCH($A52,Objekte!$Z$2:$Z$201,0)),"") | E52: =IFERROR(INDEX(Objekte!$L$2:$L$201,MATCH($A52,Objekte!$Z$2:$Z$201,0)),"") | F52: =IFERROR(INDEX(Objekte!$N$2:$N$201,MATCH($A52,Objekte!$Z$2:$Z$201,0)),"") | G52: =IFERROR(INDEX(Objekte!$P$2:$P$201,MATCH($A52,Objekte!$Z$2:$Z$201,0)),"") | H52: =IFERROR(INDEX(Objekte!$E$2:$E$201,MATCH($A52,Objekte!$Z$2:$Z$201,0)),"") | I52: =IFERROR(INDEX(Objekte!$G$2:$G$201,MATCH($A52,Objekte!$Z$2:$Z$201,0)),"") | J52: =IFERROR(INDEX(Objekte!$I$2:$I$201,MATCH($A52,Objekte!$Z$2:$Z$201,0)),"") | K52: =IFERROR(INDEX(Objekte!$Q$2:$Q$201,MATCH($A52,Objekte!$Z$2:$Z$201,0)),"") | L52: =IFERROR(INDEX(Objekte!$V$2:$V$201,MATCH($A52,Objekte!$Z$2:$Z$201,0)),"") | M52: =IFERROR(INDEX(Objekte!$D$2:$D$201,MATCH($A52,Objekte!$Z$2:$Z$201,0)),"") | N52: =IFERROR(INDEX(Objekte!$U$2:$U$201,MATCH($A52,Objekte!$Z$2:$Z$201,0)),"") | O52: =IFERROR(INDEX(Objekte!$AF$2:$AF$201,MATCH($A52,Objekte!$Z$2:$Z$201,0)),"") | P52: =IFERROR(INDEX(Objekte!$C$2:$C$201,MATCH($A52,Objekte!$Z$2:$Z$201,0)),"") | Q52: =IFERROR(INDEX(Objekte!$AD$2:$AD$201,MATCH($A52,Objekte!$Z$2:$Z$201,0)),"") | R52: =IFERROR(INDEX(Objekte!$AB$2:$AB$201,MATCH($A52,Objekte!$Z$2:$Z$201,0)),"")
B53: =IFERROR(INDEX(Objekte!$B$2:$B$201,MATCH($A53,Objekte!$Z$2:$Z$201,0)),"") | C53: =IFERROR(INDEX(Objekte!$X$2:$X$201,MATCH($A53,Objekte!$Z$2:$Z$201,0)),"") | D53: =IFERROR(INDEX(Objekte!$W$2:$W$201,MATCH($A53,Objekte!$Z$2:$Z$201,0)),"") | E53: =IFERROR(INDEX(Objekte!$L$2:$L$201,MATCH($A53,Objekte!$Z$2:$Z$201,0)),"") | F53: =IFERROR(INDEX(Objekte!$N$2:$N$201,MATCH($A53,Objekte!$Z$2:$Z$201,0)),"") | G53: =IFERROR(INDEX(Objekte!$P$2:$P$201,MATCH($A53,Objekte!$Z$2:$Z$201,0)),"") | H53: =IFERROR(INDEX(Objekte!$E$2:$E$201,MATCH($A53,Objekte!$Z$2:$Z$201,0)),"") | I53: =IFERROR(INDEX(Objekte!$G$2:$G$201,MATCH($A53,Objekte!$Z$2:$Z$201,0)),"") | J53: =IFERROR(INDEX(Objekte!$I$2:$I$201,MATCH($A53,Objekte!$Z$2:$Z$201,0)),"") | K53: =IFERROR(INDEX(Objekte!$Q$2:$Q$201,MATCH($A53,Objekte!$Z$2:$Z$201,0)),"") | L53: =IFERROR(INDEX(Objekte!$V$2:$V$201,MATCH($A53,Objekte!$Z$2:$Z$201,0)),"") | M53: =IFERROR(INDEX(Objekte!$D$2:$D$201,MATCH($A53,Objekte!$Z$2:$Z$201,0)),"") | N53: =IFERROR(INDEX(Objekte!$U$2:$U$201,MATCH($A53,Objekte!$Z$2:$Z$201,0)),"") | O53: =IFERROR(INDEX(Objekte!$AF$2:$AF$201,MATCH($A53,Objekte!$Z$2:$Z$201,0)),"") | P53: =IFERROR(INDEX(Objekte!$C$2:$C$201,MATCH($A53,Objekte!$Z$2:$Z$201,0)),"") | Q53: =IFERROR(INDEX(Objekte!$AD$2:$AD$201,MATCH($A53,Objekte!$Z$2:$Z$201,0)),"") | R53: =IFERROR(INDEX(Objekte!$AB$2:$AB$201,MATCH($A53,Objekte!$Z$2:$Z$201,0)),"")
Q54: =IFERROR(INDEX(Objekte!$AD$2:$AD$201,MATCH($A54,Objekte!$Z$2:$Z$201,0)),"") | R54: =IFERROR(INDEX(Objekte!$AB$2:$AB$201,MATCH($A54,Objekte!$Z$2:$Z$201,0)),"")
Q55: =IFERROR(INDEX(Objekte!$AD$2:$AD$201,MATCH($A55,Objekte!$Z$2:$Z$201,0)),"") | R55: =IFERROR(INDEX(Objekte!$AB$2:$AB$201,MATCH($A55,Objekte!$Z$2:$Z$201,0)),"")
Q56: =IFERROR(INDEX(Objekte!$AD$2:$AD$201,MATCH($A56,Objekte!$Z$2:$Z$201,0)),"") | R56: =IFERROR(INDEX(Objekte!$AB$2:$AB$201,MATCH($A56,Objekte!$Z$2:$Z$201,0)),"")
Q57: =IFERROR(INDEX(Objekte!$AD$2:$AD$201,MATCH($A57,Objekte!$Z$2:$Z$201,0)),"") | R57: =IFERROR(INDEX(Objekte!$AB$2:$AB$201,MATCH($A57,Objekte!$Z$2:$Z$201,0)),"")
Q58: =IFERROR(INDEX(Objekte!$AD$2:$AD$201,MATCH($A58,Objekte!$Z$2:$Z$201,0)),"") | R58: =IFERROR(INDEX(Objekte!$AB$2:$AB$201,MATCH($A58,Objekte!$Z$2:$Z$201,0)),"")
Q59: =IFERROR(INDEX(Objekte!$AD$2:$AD$201,MATCH($A59,Objekte!$Z$2:$Z$201,0)),"") | R59: =IFERROR(INDEX(Objekte!$AB$2:$AB$201,MATCH($A59,Objekte!$Z$2:$Z$201,0)),"")
Q60: =IFERROR(INDEX(Objekte!$AD$2:$AD$201,MATCH($A60,Objekte!$Z$2:$Z$201,0)),"") | R60: =IFERROR(INDEX(Objekte!$AB$2:$AB$201,MATCH($A60,Objekte!$Z$2:$Z$201,0)),"")
Q61: =IFERROR(INDEX(Objekte!$AD$2:$AD$201,MATCH($A61,Objekte!$Z$2:$Z$201,0)),"") | R61: =IFERROR(INDEX(Objekte!$AB$2:$AB$201,MATCH($A61,Objekte!$Z$2:$Z$201,0)),"")
Q62: =IFERROR(INDEX(Objekte!$AD$2:$AD$201,MATCH($A62,Objekte!$Z$2:$Z$201,0)),"") | R62: =IFERROR(INDEX(Objekte!$AB$2:$AB$201,MATCH($A62,Objekte!$Z$2:$Z$201,0)),"")
Q63: =IFERROR(INDEX(Objekte!$AD$2:$AD$201,MATCH($A63,Objekte!$Z$2:$Z$201,0)),"") | R63: =IFERROR(INDEX(Objekte!$AB$2:$AB$201,MATCH($A63,Objekte!$Z$2:$Z$201,0)),"")
Q64: =IFERROR(INDEX(Objekte!$AD$2:$AD$201,MATCH($A64,Objekte!$Z$2:$Z$201,0)),"") | R64: =IFERROR(INDEX(Objekte!$AB$2:$AB$201,MATCH($A64,Objekte!$Z$2:$Z$201,0)),"")
Q65: =IFERROR(INDEX(Objekte!$AD$2:$AD$201,MATCH($A65,Objekte!$Z$2:$Z$201,0)),"") | R65: =IFERROR(INDEX(Objekte!$AB$2:$AB$201,MATCH($A65,Objekte!$Z$2:$Z$201,0)),"")
... Q203: =IFERROR(INDEX(Objekte!$AD$2:$AD$201,MATCH($A203,Objekte!$Z$2:$Z$201,0)),"") | R203: =IFERROR(INDEX(Objekte!$AB$2:$AB$201,MATCH($A203,Objekte!$Z$2:$Z$201,0)),"")
